<?xml version="1.0" encoding="UTF-8"?>

<CHAT xmlns:xsi="http://www.w3.org/2001/XMLSchema-instance"
      xmlns="http://www.talkbank.org/ns/talkbank"
      xsi:schemaLocation="http://www.talkbank.org/ns/talkbank http://talkbank.org/software/talkbank.xsd"
      PID="11312/c-00026681-1"
      Version="2.1.0"
      Lang="est"
      Corpus="Kohler"
      Date="2002-01-09">
  <Participants>
    <participant
      id="CHI"
    name="Sandor"
      role="Target_Child"
      language="est"
      age="P2Y2M22D"

    />
    <participant
      id="FAT"
      role="Father"
      language="est"

    />
    <participant
      id="KAJ"
    name="Kaja"
      role="Investigator"
      language="est"

    />
  </Participants>
  <comment type="Date">09-JAN-2002</comment>
  <comment type="Generic">Hommikul kell 9.30-9.55 lindistaja juures kodus elutoas</comment>
  <u who="FAT" uID="u0">
    <w>näed</w>
    <pause symbolic-length="simple"/>
    <w>kes</w>
    <w>see</w>
    <w>on</w>
    <t type="q"></t>

    <a type="comments">vaadatakse raamatut</a>
  </u>
  <u who="CHI" uID="u1">
    <w>näe</w>
    <pause symbolic-length="simple"/>
    <w>lind</w>
    <w>on</w>
    <t type="p"></t>

  </u>
  <u who="FAT" uID="u2">
    <w>aga</w>
    <w>see</w>
    <t type="q"></t>

  </u>
  <u who="CHI" uID="u3">
    <w>see</w>
    <w>on</w>
    <w>konn</w>
    <t type="p"></t>

  </u>
  <u who="FAT" uID="u4">
    <w>see</w>
    <w>on</w>
    <w>konn</w>
    <t type="p"></t>

  </u>
  <u who="CHI" uID="u5">
    <w>jah</w>
    <t type="p"></t>

  </u>
  <u who="FAT" uID="u6">
    <w>aga</w>
    <w>see</w>
    <t type="q"></t>

  </u>
  <u who="CHI" uID="u7">
    <w>kukk</w>
    <t type="p"></t>

  </u>
  <u who="FAT" uID="u8">
    <g><w>kukk</w><ga type="comments">imit</ga></g>
    <t type="q"></t>

  </u>
  <u who="CHI" uID="u9">
    <w>jah</w>
    <t type="p"></t>

  </u>
  <u who="FAT" uID="u10">
    <w>äkki</w>
    <w>on</w>
    <w>kana</w>
    <t type="q"></t>

  </u>
  <u who="CHI" uID="u11">
    <w>näe</w>
    <w>siin</w>
    <pause symbolic-length="simple"/>
    <g><w>on</w><ga type="comments">imit</ga></g>
    <t type="p"></t>

  </u>
  <u who="FAT" uID="u12">
    <g><w>see</w><k type="retracing with correction"/></g>
    <w>kes</w>
    <w>see</w>
    <w>on</w>
    <t type="q"></t>

  </u>
  <u who="CHI" uID="u13">
    <w untranscribed="unintelligible">xxx</w>
    <t type="p"></t>

  </u>
  <u who="FAT" uID="u14">
    <w>lammas</w>
    <w>on</w>
    <t type="p"></t>

  </u>
  <u who="CHI" uID="u15">
    <w>jah</w>
    <pause symbolic-length="simple"/>
    <g><w>lammas</w><ga type="comments">imit</ga></g>
    <t type="p"></t>

  </u>
  <u who="FAT" uID="u16">
    <w>jah</w>
    <pause symbolic-length="simple"/>
    <w>a'</w>
    <w>kes</w>
    <w>see</w>
    <w>on</w>
    <t type="q"></t>

  </u>
  <u who="CHI" uID="u17">
    <w>see</w>
    <w>on</w>
    <w>mõmmi</w>
    <t type="p"></t>

  </u>
  <u who="FAT" uID="u18">
    <w>karumõmmi</w>
    <t type="p"></t>

  </u>
  <u who="CHI" uID="u19">
    <w>jah</w>
    <t type="p"></t>

  </u>
  <u who="FAT" uID="u20">
    <w>a'</w>
    <w>kes</w>
    <w>see</w>
    <w>on</w>
    <t type="q"></t>

  </u>
  <u who="CHI" uID="u21">
    <w>sellega</w>
    <t type="p"></t>

    <a type="comments">SAN köhib</a>
  </u>
  <u who="CHI" uID="u22">
    <w>see</w>
    <g><w>on</w><ga type="comments">imit</ga></g>
    <w>kukk</w>
    <t type="p"></t>

  </u>
  <u who="FAT" uID="u23">
    <w>lehm</w>
    <t type="p"></t>

  </u>
  <u who="CHI" uID="u24">
    <w>aa</w>
    <t type="e"></t>

  </u>
  <u who="FAT" uID="u25">
    <w>lehm</w>
    <w>on</w>
    <pause symbolic-length="simple"/>
    <w>muu</w>
    <t type="e"></t>

  </u>
  <u who="CHI" uID="u26">
    <e><action/></e>
    <t type="p"></t>

  </u>
  <u who="FAT" uID="u27">
    <w>vaata</w>
    <w>veel</w>
    <w>kes</w>
    <w>siin</w>
    <w>on</w>
    <pause symbolic-length="simple"/>
    <pause symbolic-length="simple"/>
    <w>vaata</w>
    <w>näed</w>
    <pause symbolic-length="simple"/>
    <w>siin</w>
    <w>on</w>
    <pause symbolic-length="simple"/>
    <w>siin</w>
    <w>on</w>
    <w>riided</w>
    <t type="p"></t>

    <a type="actions">kehitseb raamatut</a>
  </u>
  <u who="FAT" uID="u28">
    <w>mis</w>
    <w>siin</w>
    <w>on</w>
    <pause symbolic-length="simple"/>
    <w>kes</w>
    <w>see</w>
    <w>on</w>
    <t type="q"></t>

  </u>
  <u who="CHI" uID="u29">
    <w>näe</w>
    <t type="e"></t>

  </u>
  <u who="FAT" uID="u30">
    <w>kes</w>
    <w>see</w>
    <w>on</w>
    <t type="q"></t>

  </u>
  <u who="CHI" uID="u31">
    <g><w>see</w>
    <w>on</w><ga type="comments">imit</ga></g>
    <t type="p"></t>

  </u>
  <u who="FAT" uID="u32">
    <w>elevant</w>
    <t type="p"></t>

  </u>
  <u who="CHI" uID="u33">
    <g><w>levant<replacement><w>elevant</w></replacement></w><ga type="comments">imit</ga></g>
    <t type="p"></t>

  </u>
  <u who="FAT" uID="u34">
    <w>kes</w>
    <w>see</w>
    <w>on</w>
    <t type="q"></t>

    <a type="actions">näitab krokodilli</a>
  </u>
  <u who="CHI" uID="u35">
    <e><action/></e>
    <t type="p"></t>

    <a type="comments">SAN köhib</a>
  </u>
  <u who="FAT" uID="u36">
    <g><w>kes</w>
    <w>see</w>
    <w>on</w><k type="retracing"/></g>
    <pause symbolic-length="simple"/>
    <w>kes</w>
    <w>see</w>
    <w>on</w>
    <t type="q"></t>

  </u>
  <u who="CHI" uID="u37">
    <e><action/></e>
    <t type="p"></t>

  </u>
  <u who="KAJ" uID="u38">
    <w>krokodill</w>
    <w>on</w>
    <pause symbolic-length="simple"/>
    <w>vaata</w>
    <w>kui</w>
    <w>suur</w>
    <w>suu</w>
    <w>tal</w>
    <w>on</w>
    <pause symbolic-length="simple"/>
    <w>hambad</w>
    <w>ja</w>
    <t type="trail off"></t>

  </u>
  <u who="KAJ" uID="u39">
    <w>mis</w>
    <w>ta</w>
    <w>teeb</w>
    <w>sihukese</w>
    <w>suure</w>
    <w>suuga</w>
    <t type="q"></t>

  </u>
  <u who="CHI" uID="u40">
    <w>näe</w>
    <w untranscribed="unintelligible">xxx</w>
    <w>näe</w>
    <t type="e"></t>

    <a type="actions">näitab tigu</a>
  </u>
  <u who="KAJ" uID="u41">
    <w>tigu</w>
    <t type="e"></t>

  </u>
  <u who="CHI" uID="u42">
    <g><w>tigu</w><ga type="comments">imit</ga></g>
    <t type="p"></t>

  </u>
  <u who="KAJ" uID="u43">
    <w>a'</w>
    <w>mis</w>
    <w>see</w>
    <w>krokodill</w>
    <w>teeb</w>
    <w>sellise</w>
    <w>suure</w>
    <w>suuga</w>
    <t type="q"></t>

  </u>
  <u who="CHI" uID="u44">
    <e><action/></e>
    <t type="p"></t>

  </u>
  <u who="FAT" uID="u45">
    <freecode>sosinal</freecode>
    <w>mamm<wk type="cmp"/>mamm</w>
    <t type="p"></t>

  </u>
  <u who="CHI" uID="u46">
    <freecode>sosinal</freecode>
    <g><w>mamm<wk type="cmp"/>mamm</w><ga type="comments">imit</ga></g>
    <t type="p"></t>

  </u>
  <u who="FAT" uID="u47">
    <w>jah</w>
    <t type="p"></t>

  </u>
  <u who="FAT" uID="u48">
    <w>näed</w>
    <pause symbolic-length="simple"/>
    <w>see</w>
    <w>on</w>
    <w>haikala</w>
    <t type="e"></t>

  </u>
  <u who="CHI" uID="u49">
    <w>näe</w>
    <pause symbolic-length="simple"/>
    <g><w>haikala</w><ga type="comments">imit</ga></g>
    <t type="e"></t>

  </u>
  <u who="KAJ" uID="u50">
    <w>haikala</w>
    <w>jah</w>
    <t type="p"></t>

  </u>
  <u who="FAT" uID="u51">
    <w>kes</w>
    <w>see</w>
    <w>on</w>
    <pause symbolic-length="simple"/>
    <w>hüppab</w>
    <w>hoppadi<wk type="cmp"/>hopsti</w>
    <t type="p"></t>

    <a type="actions">näitab kängurule</a>
  </u>
  <u who="FAT" uID="u52">
    <w>känguru</w>
    <t type="e"></t>

  </u>
  <u who="CHI" uID="u53">
    <w>jah</w>
    <t type="p"></t>

  </u>
  <u who="FAT" uID="u54">
    <w>aga</w>
    <w>see</w>
    <t type="q"></t>

  </u>
  <u who="CHI" uID="u55">
    <w>see</w>
    <g><w>on</w><ga type="comments">imit</ga></g>
    <pause symbolic-length="simple"/>
    <w>tiigel<replacement><w>tiiger</w></replacement></w>
    <t type="p"></t>

  </u>
  <u who="FAT" uID="u56">
    <w>ongi</w>
    <pause symbolic-length="simple"/>
    <w>aga</w>
    <w>kes</w>
    <w>see</w>
    <w>on</w>
    <t type="q"></t>

  </u>
  <u who="CHI" uID="u57">
    <w>see</w>
    <g><w>on</w><ga type="comments">imit</ga></g>
    <w>olal<replacement><w>orav</w></replacement></w>
    <t type="p"></t>

  </u>
  <u who="FAT" uID="u58">
    <w>orav</w>
    <w>jah</w>
    <t type="p"></t>

  </u>
  <u who="FAT" uID="u59">
    <w>aga</w>
    <w>kes</w>
    <w>see</w>
    <w>on</w>
    <t type="q"></t>

  </u>
  <u who="CHI" uID="u60">
    <w>see</w>
    <g><w>on</w><ga type="comments">imit</ga></g>
    <w>repad<wk type="cmp"/>rein<replacement><w>rebase<wk type="cmp"/>rein</w></replacement></w>
    <t type="p"></t>

  </u>
  <u who="FAT" uID="u61">
    <w>ei</w>
    <w>ole</w>
    <pause symbolic-length="simple"/>
    <w>see</w>
    <w>on</w>
    <w>rebane</w>
    <t type="e"></t>

  </u>
  <u who="CHI" uID="u62">
    <w>näe</w>
    <t type="e"></t>

    <a type="actions">näitab uut pilti</a>
  </u>
  <u who="KAJ" uID="u63">
    <w>jah</w>
    <pause symbolic-length="simple"/>
    <w>poiss</w>
    <t type="e"></t>

  </u>
  <u who="KAJ" uID="u64">
    <w>a'</w>
    <w>vaata</w>
    <pause symbolic-length="simple"/>
    <w>kes</w>
    <w>need</w>
    <w>on</w>
    <t type="q"></t>

  </u>
  <u who="CHI" uID="u65">
    <w>iiled<replacement><w>hiired</w></replacement></w>
    <t type="p"></t>

  </u>
  <u who="KAJ" uID="u66">
    <w>jah</w>
    <pause symbolic-length="simple"/>
    <w>mis</w>
    <w>nad</w>
    <w>teevad</w>
    <t type="q"></t>

  </u>
  <u who="CHI" uID="u67">
    <w>näe</w>
    <w>kutsa</w>
    <t type="e"></t>

  </u>
  <u who="KAJ" uID="u68">
    <w>jah</w>
    <pause symbolic-length="simple"/>
    <w>a'</w>
    <w>mis</w>
    <w>need</w>
    <w>hiired</w>
    <w>teevad</w>
    <w>siin</w>
    <t type="q"></t>

  </u>
  <u who="CHI" uID="u69">
    <w>mamm<wk type="cmp"/>mamm<wk type="cmp"/>mamm</w>
    <g><w>teevad</w><ga type="comments">imit</ga></g>
    <w untranscribed="unintelligible">xxx</w>
    <t type="p"></t>

  </u>
  <u who="KAJ" uID="u70">
    <w>teevad</w>
    <t type="q"></t>

  </u>
  <u who="KAJ" uID="u71">
    <w>ma</w>
    <w>mõtlesin</w>
    <w>et</w>
    <w>istuvad</w>
    <w>ja</w>
    <w>vaatavad</w>
    <t type="p"></t>

  </u>
  <u who="CHI" uID="u72">
    <w>jah</w>
    <t type="p"></t>

  </u>
  <u who="KAJ" uID="u73">
    <w>a'</w>
    <w>kutsad</w>
    <w>hüppavad</w>
    <w>ju</w>
    <t type="e"></t>

  </u>
  <u who="CHI" uID="u74">
    <w>jah</w>
    <t type="p"></t>

  </u>
  <u who="KAJ" uID="u75">
    <w>kuhu</w>
    <w>nad</w>
    <w>hüppavad</w>
    <t type="q"></t>

  </u>
  <u who="CHI" uID="u76">
    <g><w>näe</w><k type="retracing"/></g>
    <w>näe</w>
    <w>hobu<replacement><w>hobune</w></replacement></w>
    <pause symbolic-length="simple"/>
    <w>näe</w>
    <t type="e"></t>

    <a type="actions">näitab uut pilti</a>
  </u>
  <u who="KAJ" uID="u77">
    <w>mhmh</w>
    <t type="p"></t>

  </u>
  <u who="CHI" uID="u78">
    <w>näe</w>
    <pause symbolic-length="simple"/>
    <pause symbolic-length="simple"/>
    <w>onu</w>
    <t type="p"></t>

  </u>
  <u who="FAT" uID="u79">
    <w>see</w>
    <w>on</w>
    <w>väike</w>
    <w>tita</w>
    <w>seal</w>
    <t type="p"></t>

  </u>
  <u who="CHI" uID="u80">
    <w>näe</w>
    <w>lauavad<replacement><w>laulavad</w></replacement></w>
    <t type="p"></t>

  </u>
  <u who="FAT" uID="u81">
    <w>laulavad</w>
    <t type="q"></t>

  </u>
  <u who="KAJ" uID="u82">
    <w>jaa</w>
    <pause symbolic-length="simple"/>
    <w>ja</w>
    <w>mängivad</w>
    <w>pilli</w>
    <w>ja</w>
    <t type="trail off"></t>

  </u>
  <u who="CHI" uID="u83">
    <w>näe</w>
    <t type="e"></t>

  </u>
  <u who="FAT" uID="u84">
    <w>mis</w>
    <w>see</w>
    <w>on</w>
    <t type="q"></t>

  </u>
  <u who="CHI" uID="u85">
    <g><w>see</w>
    <w>on</w><ga type="comments">imit</ga></g>
    <w>uts<replacement><w>uks</w></replacement></w>
    <t type="p"></t>

  </u>
  <u who="FAT" uID="u86">
    <w>uks</w>
    <t type="p"></t>

  </u>
  <u who="KAJ" uID="u87">
    <g><w>kus</w>
    <w>ukselink</w>
    <w>on</w><k type="retracing with correction"/></g>
    <w>kus</w>
    <w>sa</w>
    <w>ukse</w>
    <w>lahti</w>
    <w>teed</w>
    <t type="q"></t>

  </u>
  <u who="CHI" uID="u88">
    <e><action/></e>
    <t type="p"></t>
    <postcode>trn</postcode>

    <a type="actions">näitab</a>
  </u>
  <u who="KAJ" uID="u89">
    <w>sealt</w>
    <pause symbolic-length="simple"/>
    <w>mhmh</w>
    <t type="p"></t>

  </u>
  <u who="CHI" uID="u90">
    <w>näe</w>
    <pause symbolic-length="simple"/>
    <w>vesi</w>
    <w>tuleb</w>
    <w>pauh</w>
    <t type="p"></t>

    <a type="actions">näitab vihmaveetoru</a>
  </u>
  <u who="FAT" uID="u91">
    <w>vesi</w>
    <w>tuleb</w>
    <w>pauh</w>
    <pause symbolic-length="simple"/>
    <w>see</w>
    <w>on</w>
    <w>vihmaveetoru</w>
    <t type="p"></t>

  </u>
  <u who="CHI" uID="u92">
    <g><w>ihmaveetolu<replacement><w>vihmaveetoru</w></replacement></w><ga type="comments">imit</ga></g>
    <pause symbolic-length="simple"/>
    <w>õue</w>
    <w>pauh</w>
    <t type="p"></t>

  </u>
  <u who="FAT" uID="u93">
    <w>just</w>
    <t type="p"></t>

  </u>
  <u who="KAJ" uID="u94">
    <w>a'</w>
    <w>kus</w>
    <w>korsten</w>
    <w>on</w>
    <t type="q"></t>

  </u>
  <u who="KAJ" uID="u95">
    <w>kortsen</w>
    <w>ka</w>
    <w>peal</w>
    <t type="e"></t>

  </u>
  <u who="FAT" uID="u96">
    <w>kust</w>
    <w>suitsu</w>
    <w>tuleb</w>
    <t type="q"></t>

  </u>
  <u who="CHI" uID="u97">
    <w>siit</w>
    <g><w>uistu<replacement><w>suitsu</w></replacement></w><ga type="comments">imit</ga></g>
    <t type="p"></t>

    <a type="actions">näitab</a>
  </u>
  <u who="KAJ" uID="u98">
    <w>sealt</w>
    <w>ülevalt</w>
    <w>jah</w>
    <t type="q"></t>

  </u>
  <u who="CHI" uID="u99">
    <w>jah</w>
    <t type="p"></t>

  </u>
  <u who="CHI" uID="u100">
    <w>siit</w>
    <w>selle</w>
    <w>seest</w>
    <t type="p"></t>

  </u>
  <u who="KAJ" uID="u101">
    <w>jah</w>
    <w>täpselt</w>
    <w>sealt</w>
    <w>selle</w>
    <w>seest</w>
    <t type="p"></t>

  </u>
  <u who="FAT" uID="u102">
    <w>a'</w>
    <w>kus</w>
    <w>maja</w>
    <w>on</w>
    <t type="q"></t>

  </u>
  <u who="CHI" uID="u103">
    <w>siin</w>
    <g><w>maja</w><ga type="comments">imit</ga></g>
    <t type="e"></t>

  </u>
  <u who="FAT" uID="u104">
    <w>see</w>
    <t type="p"></t>

  </u>
  <u who="CHI" uID="u105">
    <g><w>see</w>
    <pause symbolic-length="simple"/>
    <w>maja</w><ga type="comments">imit</ga></g>
    <t type="e"></t>

  </u>
  <u who="FAT" uID="u106">
    <w>ahah</w>
    <t type="p"></t>

  </u>
  <u who="CHI" uID="u107">
    <g><w>kukkus</w>
    <w>maha</w><k type="retracing with correction"/></g>
    <pause symbolic-length="simple"/>
    <w>nüüd</w>
    <w>kukkus</w>
    <w>maha</w>
    <t type="p"></t>

  </u>
  <u who="KAJ" uID="u108">
    <w>mis</w>
    <w>see</w>
    <w>maha</w>
    <w>kukkus</w>
    <pause symbolic-length="simple"/>
    <w>kortsen</w>
    <w>või</w>
    <t type="q"></t>

  </u>
  <u who="FAT" uID="u109">
    <w>oi<wk type="cmp"/>oi</w>
    <pause symbolic-length="simple"/>
    <w>siis</w>
    <w>on</w>
    <w>küll</w>
    <w>pahasti</w>
    <t type="p"></t>

  </u>
  <u who="CHI" uID="u110">
    <e><action/></e>
    <t type="p"></t>

  </u>
  <u who="FAT" uID="u111">
    <w>vaatame</w>
    <w>veel</w>
    <pause symbolic-length="simple"/>
    <w>mis</w>
    <w>siin</w>
    <w>veel</w>
    <w>on</w>
    <t type="e"></t>

    <a type="actions">lehitseb raamatut</a>
  </u>
  <u who="FAT" uID="u112">
    <w untranscribed="unintelligible">xxx</w>
    <t type="p"></t>

  </u>
  <u who="FAT" uID="u113">
    <w>näed</w>
    <w>mis</w>
    <w>see</w>
    <w>on</w>
    <t type="q"></t>

    <a type="actions">näitab lennukit</a>
  </u>
  <u who="CHI" uID="u114">
    <w>jaa</w>
    <t type="p"></t>

  </u>
  <u who="FAT" uID="u115">
    <w>lendab</w>
    <w>uu</w>
    <t type="e"></t>

  </u>
  <u who="FAT" uID="u116">
    <w>mis</w>
    <w>see</w>
    <w>on</w>
    <t type="q"></t>

  </u>
  <u who="CHI" uID="u117">
    <e><action/></e>
    <t type="p"></t>

  </u>
  <u who="FAT" uID="u118">
    <freecode>sosinal</freecode>
    <w>lennuk</w>
    <t type="p"></t>

  </u>
  <u who="CHI" uID="u119">
    <w>jah</w>
    <t type="p"></t>

  </u>
  <u who="FAT" uID="u120">
    <w>aga</w>
    <w>see</w>
    <t type="q"></t>

  </u>
  <u who="CHI" uID="u121">
    <w>ei</w>
    <w>ole</w>
    <w untranscribed="unintelligible">xxx</w>
    <t type="p"></t>

  </u>
  <u who="FAT" uID="u122">
    <w>see</w>
    <w>on</w>
    <w>laev</w>
    <t type="p"></t>

  </u>
  <u who="CHI" uID="u123">
    <w>jah</w>
    <g><w>laev</w><ga type="comments">imit</ga></g>
    <t type="p"></t>

    <a type="comments">SAN köhib</a>
  </u>
  <u who="FAT" uID="u124">
    <w>kes</w>
    <w>see</w>
    <w>on</w>
    <t type="q"></t>

  </u>
  <u who="CHI" uID="u125">
    <w>ei</w>
    <w>tea</w>
    <t type="p"></t>

  </u>
  <u who="FAT" uID="u126">
    <w>vanaisa</w>
    <t type="p"></t>

  </u>
  <u who="FAT" uID="u127">
    <w>vanaema</w>
    <t type="p"></t>

  </u>
  <u who="FAT" uID="u128">
    <w>ema</w>
    <t type="p"></t>

  </u>
  <u who="FAT" uID="u129">
    <w>kus</w>
    <w>on</w>
    <w>ema</w>
    <t type="q"></t>

  </u>
  <u who="CHI" uID="u130">
    <e><action/></e>
    <t type="p"></t>

  </u>
  <u who="FAT" uID="u131">
    <w>näed</w>
    <w>siin</w>
    <t type="e"></t>

  </u>
  <u who="FAT" uID="u132">
    <w>kes</w>
    <w>see</w>
    <w>on</w>
    <t type="q"></t>

  </u>
  <u who="CHI" uID="u133">
    <e><action/></e>
    <t type="p"></t>

    <a type="actions">keerab lehte</a>
  </u>
  <u who="KAJ" uID="u134">
    <w>tüdruk</w>
    <w>on</w>
    <w>seal</w>
    <t type="e"></t>

  </u>
  <u who="FAT" uID="u135">
    <w>ei</w>
    <w>ole</w>
    <pause symbolic-length="simple"/>
    <w>on</w>
    <w>või</w>
    <t type="q"></t>

  </u>
  <u who="CHI" uID="u136">
    <freecode>sosinal</freecode>
    <w untranscribed="unintelligible">xxx</w>
    <w>siin</w>
    <w>vaata</w>
    <t type="p"></t>

    <a type="actions">võtab FAT-i käe ja paneb pildi peale</a>
  </u>
  <u who="FAT" uID="u137">
    <w>see</w>
    <w>on</w>
    <w>tüdruk</w>
    <t type="p"></t>

  </u>
  <u who="CHI" uID="u138">
    <freecode>sosinal</freecode>
    <w>issi</w>
    <w>katsu</w>
    <t type="p"></t>

  </u>
  <u who="FAT" uID="u139">
    <w>ma</w>
    <w>katsun</w>
    <w>jah</w>
    <t type="p"></t>

  </u>
  <u who="KAJ" uID="u140">
    <w>ütleb</w>
    <w>et</w>
    <w>katsu</w>
    <w>või</w>
    <t type="q"></t>

    <a type="addressee">FAT</a>
  </u>
  <u who="FAT" uID="u141">
    <w>jah</w>
    <t type="p"></t>

  </u>
  <u who="FAT" uID="u142">
    <w>kus</w>
    <w>poiss</w>
    <w>on</w>
    <t type="q"></t>

  </u>
  <u who="CHI" uID="u143">
    <e><action/></e>
    <t type="p"></t>
    <postcode>trn</postcode>

    <a type="actions">näitab vanaemale</a>
  </u>
  <u who="FAT" uID="u144">
    <w>see</w>
    <w>on</w>
    <w>vanaema</w>
    <pause symbolic-length="simple"/>
    <w>poiss</w>
    <w>on</w>
    <w>tüdruku</w>
    <w>kõrval</w>
    <w>näe</w>
    <pause symbolic-length="simple"/>
    <w>tüdruk</w>
    <w>on</w>
    <w>siin</w>
    <pause symbolic-length="simple"/>
    <w>poiss</w>
    <w>on</w>
    <w>see</w>
    <w>jah</w>
    <t type="p"></t>

  </u>
  <u who="CHI" uID="u145">
    <e><action/></e>
    <t type="p"></t>

    <a type="actions">veab FAT-i sõrmi mööda pilte</a>
  </u>
  <u who="FAT" uID="u146">
    <w>kes</w>
    <w>see</w>
    <w>on</w>
    <t type="q"></t>

  </u>
  <u who="FAT" uID="u147">
    <w>tita</w>
    <t type="p"></t>

  </u>
  <u who="FAT" uID="u148">
    <w>vaatame</w>
    <w>edasi</w>
    <t type="e"></t>

    <a type="actions">keerab lehte</a>
  </u>
  <u who="FAT" uID="u149">
    <w>nii</w>
    <pause symbolic-length="simple"/>
    <w>mis</w>
    <w>siin</w>
    <w>tuleb</w>
    <t type="p"></t>

  </u>
  <u who="FAT" uID="u150">
    <w>oi</w>
    <pause symbolic-length="simple"/>
    <g><w>kes</w>
    <w>siin</w>
    <w>on</w><k type="retracing with correction"/></g>
    <w>kes</w>
    <w>see</w>
    <w>on</w>
    <t type="q"></t>

  </u>
  <u who="CHI" uID="u151">
    <w>kass</w>
    <t type="p"></t>

  </u>
  <u who="KAJ" uID="u152">
    <w>ongi</w>
    <w>kass</w>
    <t type="e"></t>

  </u>
  <u who="FAT" uID="u153">
    <w>kass</w>
    <w>on</w>
    <w>voodis</w>
    <t type="p"></t>

  </u>
  <u who="FAT" uID="u154">
    <w>mis</w>
    <w>kass</w>
    <w>voodis</w>
    <w>teeb</w>
    <t type="q"></t>

  </u>
  <u who="CHI" uID="u155">
    <w>näu</w>
    <t type="p"></t>

  </u>
  <u who="FAT" uID="u156">
    <w>miau</w>
    <w>teeb</w>
    <t type="q"></t>

  </u>
  <u who="FAT" uID="u157">
    <w>a'</w>
    <w>kes</w>
    <w>see</w>
    <w>on</w>
    <t type="q"></t>

  </u>
  <u who="CHI" uID="u158">
    <freecode>sosinal</freecode>
    <g><w>see</w>
    <w>on</w><ga type="comments">imit</ga></g>
    <w>mõmmi</w>
    <t type="p"></t>

  </u>
  <u who="FAT" uID="u159">
    <w>mõmmi</w>
    <t type="q"></t>

  </u>
  <u who="CHI" uID="u160">
    <freecode>sosinal</freecode>
    <w>jah</w>
    <t type="p"></t>

  </u>
  <u who="FAT" uID="u161">
    <w>mõmmi</w>
    <w>ka</w>
    <w>voodis</w>
    <t type="q"></t>

  </u>
  <u who="FAT" uID="u162">
    <w>oi<wk type="cmp"/>oi</w>
    <t type="e"></t>

  </u>
  <u who="FAT" uID="u163">
    <w>a'</w>
    <w>mis</w>
    <w>siin</w>
    <w>on</w>
    <t type="q"></t>

  </u>
  <u who="CHI" uID="u164">
    <w untranscribed="unintelligible">xxx</w>
    <t type="p"></t>

  </u>
  <u who="FAT" uID="u165">
    <w>mis</w>
    <w>poisil</w>
    <w>käes</w>
    <w>on</w>
    <t type="q"></t>

  </u>
  <u who="CHI" uID="u166">
    <freecode>sosinal</freecode>
    <w>pall</w>
    <g><w>on</w>
    <w>käes</w><ga type="comments">imit</ga></g>
    <t type="p"></t>

  </u>
  <u who="FAT" uID="u167">
    <w>pall</w>
    <w>on</w>
    <w>käes</w>
    <t type="p"></t>

  </u>
  <u who="KAJ" uID="u168">
    <w>mis</w>
    <w>nad</w>
    <w>teevad</w>
    <w>palliga</w>
    <t type="q"></t>

  </u>
  <u who="CHI" uID="u169">
    <w>pauhti</w>
    <t type="p"></t>

  </u>
  <u who="KAJ" uID="u170">
    <w>pauhti</w>
    <w>mängivad</w>
    <t type="p"></t>

  </u>
  <u who="KAJ" uID="u171">
    <g><w>sina</w>
    <w>ka</w>
    <w>mängid</w>
    <w>palliga</w><k type="retracing with correction"/></g>
    <w>sul</w>
    <w>on</w>
    <w>pall</w>
    <w>või</w>
    <t type="q"></t>

  </u>
  <u who="CHI" uID="u172">
    <e><action/></e>
    <t type="p"></t>

  </u>
  <u who="FAT" uID="u173">
    <w>ütle</w>
    <w>et</w>
    <w>sul</w>
    <w>on</w>
    <w>õhupall</w>
    <w>kodus</w>
    <t type="e"></t>

  </u>
  <u who="CHI" uID="u174">
    <g><w>õhupall</w>
    <w>kodus</w>
    <w>on</w><ga type="comments">imit</ga></g>
    <t type="p"></t>

  </u>
  <u who="KAJ" uID="u175">
    <w>ahah</w>
    <pause symbolic-length="simple"/>
    <w>mängid</w>
    <w>ka</w>
    <w>sellega</w>
    <w>või</w>
    <t type="q"></t>

  </u>
  <u who="CHI" uID="u176">
    <w>jaa</w>
    <t type="p"></t>

  </u>
  <u who="KAJ" uID="u177">
    <w>Sanna</w>
    <w>ka</w>
    <w>mängib</w>
    <w>või</w>
    <t type="q"></t>

  </u>
  <u who="CHI" uID="u178">
    <w>jaa</w>
    <t type="p"></t>

  </u>
  <u who="KAJ" uID="u179">
    <w>aga</w>
    <w>emme</w>
    <t type="q"></t>

  </u>
  <u who="CHI" uID="u180">
    <w>jaa</w>
    <t type="p"></t>

  </u>
  <u who="KAJ" uID="u181">
    <w>kolmekesi</w>
    <w>mängite</w>
    <w>jah</w>
    <t type="q"></t>

  </u>
  <u who="CHI" uID="u182">
    <w>jah</w>
    <t type="p"></t>

  </u>
  <u who="FAT" uID="u183">
    <w>ja</w>
    <w>siis</w>
    <w>ütle</w>
    <w>et</w>
    <w>suur</w>
    <w>push<wk type="cmp"/>pall</w>
    <w>on</w>
    <w>ka</w>
    <t type="e"></t>

  </u>
  <u who="CHI" uID="u184">
    <g><w>puh<wk type="cmp"/>pall<replacement><w>push<wk type="cmp"/>pall</w></replacement></w>
    <w>ka</w><ga type="comments">imit</ga></g>
    <t type="p"></t>

  </u>
  <u who="FAT" uID="u185">
    <w>jaa</w>
    <t type="p"></t>

  </u>
  <u who="KAJ" uID="u186">
    <w>mhmh</w>
    <pause symbolic-length="simple"/>
    <w>ja</w>
    <w>mis</w>
    <w>te</w>
    <w>seal</w>
    <w>kodus</w>
    <w>veel</w>
    <w>teete</w>
    <w>siis</w>
    <w>Sannaga</w>
    <t type="q"></t>

  </u>
  <u who="CHI" uID="u187">
    <w>söövad</w>
    <t type="p"></t>

  </u>
  <u who="KAJ" uID="u188">
    <g><w>söövad</w><ga type="comments">imit</ga></g>
    <t type="q"></t>

  </u>
  <u who="CHI" uID="u189">
    <w>jah</w>
    <t type="p"></t>

  </u>
  <u who="KAJ" uID="u190">
    <w>mhmh</w>
    <pause symbolic-length="simple"/>
    <w>sööte</w>
    <pause symbolic-length="simple"/>
    <w>aga</w>
    <w>mide</w>
    <w>te</w>
    <w>sööte</w>
    <w>siis</w>
    <t type="q"></t>

  </u>
  <u who="CHI" uID="u191">
    <w>sööme</w>
    <w>kohu<replacement><w>kõhu</w></replacement></w>
    <w>täis</w>
    <t type="p"></t>

  </u>
  <u who="KAJ" uID="u192">
    <w>sööme</w>
    <w>kõhu</w>
    <w>täis</w>
    <w>jah</w>
    <t type="p"></t>

  </u>
  <u who="KAJ" uID="u193">
    <w>seda</w>
    <w>sööte</w>
    <pause symbolic-length="simple"/>
    <w>mid</w>
    <w>emme</w>
    <w>keedab</w>
    <pause symbolic-length="simple"/>
    <w>jah</w>
    <t type="q"></t>

  </u>
  <u who="CHI" uID="u194">
    <w>näe</w>
    <t type="e"></t>

  </u>
  <u who="FAT" uID="u195">
    <w>putru</w>
    <w>sööd</w>
    <w>sina</w>
    <w>või</w>
    <t type="q"></t>

  </u>
  <u who="CHI" uID="u196">
    <w>näe</w>
    <w>kukk</w>
    <t type="e"></t>

    <a type="actions">näitab raamatusse</a>
  </u>
  <u who="KAJ" uID="u197">
    <w>kukk</w>
    <w>on</w>
    <w>jah</w>
    <t type="p"></t>

  </u>
  <u who="CHI" uID="u198">
    <w untranscribed="unintelligible">xxx</w>
    <g><w>on</w><ga type="comments">imit</ga></g>
    <t type="p"></t>

  </u>
  <u who="FAT" uID="u199">
    <w>päike</w>
    <t type="p"></t>

    <a type="actions">näitab päevalillele</a>
  </u>
  <u who="CHI" uID="u200">
    <g><w>päike</w><ga type="comments">imit</ga></g>
    <t type="p"></t>

  </u>
  <u who="CHI" uID="u201">
    <w>näe</w>
    <t type="p"></t>

  </u>
  <u who="KAJ" uID="u202">
    <w>naerab</w>
    <t type="p"></t>

  </u>
  <u who="CHI" uID="u203">
    <w>jah</w>
    <t type="p"></t>

  </u>
  <u who="FAT" uID="u204">
    <w>varre</w>
    <w>otsas</w>
    <w>päike</w>
    <w>ehk</w>
    <w>lill</w>
    <t type="p"></t>

  </u>
  <u who="KAJ" uID="u205">
    <freecode>naerdes</freecode>
    <w>jah</w>
    <t type="p"></t>

    <a type="actions">lehitseb raamatut</a>
  </u>
  <u who="CHI" uID="u206">
    <w>näe</w>
    <t type="e"></t>

  </u>
  <u who="KAJ" uID="u207">
    <w>siin</w>
    <w>me</w>
    <w>juba</w>
    <w>olime</w>
    <t type="p"></t>

  </u>
  <u who="CHI" uID="u208">
    <w>näe</w>
    <t type="e"></t>

  </u>
  <u who="KAJ" uID="u209">
    <w>mhmh</w>
    <t type="p"></t>

  </u>
  <u who="KAJ" uID="u210">
    <w>tigu</w>
    <t type="p"></t>

  </u>
  <u who="CHI" uID="u211">
    <w>jah</w>
    <pause symbolic-length="simple"/>
    <g><w>tigu</w><ga type="comments">imit</ga></g>
    <t type="p"></t>

  </u>
  <u who="KAJ" uID="u212">
    <w>kus</w>
    <w>see</w>
    <w>tigu</w>
    <w>läheb</w>
    <pause symbolic-length="simple"/>
    <w>vaata</w>
    <w>ta</w>
    <w>kõnnib</w>
    <w>ära</w>
    <w>vist</w>
    <t type="p"></t>

  </u>
  <u who="CHI" uID="u213">
    <e><action/></e>
    <t type="p"></t>

  </u>
  <u who="FAT" uID="u214">
    <w>tigu</w>
    <w>läheb</w>
    <w>oma</w>
    <w>koju</w>
    <t type="p"></t>

  </u>
  <u who="CHI" uID="u215">
    <w>jah</w>
    <t type="p"></t>

  </u>
  <u who="FAT" uID="u216">
    <w>või</w>
    <w>kuhu</w>
    <w>ta</w>
    <w>läheb</w>
    <t type="q"></t>

  </u>
  <u who="CHI" uID="u217">
    <w untranscribed="unintelligible">xxx</w>
    <g><w>läheb</w>
    <w>äla<replacement><w>ära</w></replacement></w><k type="retracing"/></g>
    <w>läheb</w>
    <w>äla<replacement><w>ära</w></replacement></w>
    <w>kala</w>
    <w>uulde<replacement><w>juurde</w></replacement></w>
    <t type="p"></t>

  </u>
  <u who="FAT" uID="u218">
    <w>kala</w>
    <w>juurde</w>
    <t type="q"></t>

  </u>
  <u who="KAJ" uID="u219">
    <w>ajavad</w>
    <w>seal</w>
    <w>kalaga</w>
    <w>juttu</w>
    <w>ja</w>
    <t type="q"></t>

  </u>
  <u who="CHI" uID="u220">
    <w>jah</w>
    <t type="p"></t>

  </u>
  <u who="FAT" uID="u221">
    <w>vaatame</w>
    <w>veel</w>
    <w>mõnda</w>
    <w>pilti</w>
    <t type="q"></t>

  </u>
  <u who="CHI" uID="u222">
    <e><action/></e>
    <t type="p"></t>

  </u>
  <u who="FAT" uID="u223">
    <w>oi</w>
    <pause symbolic-length="simple"/>
    <w>kes</w>
    <w>need</w>
    <w>seal</w>
    <w>on</w>
    <t type="q"></t>

  </u>
  <u who="CHI" uID="u224">
    <w>näe</w>
    <w>konn</w>
    <t type="e"></t>

  </u>
  <u who="KAJ" uID="u225">
    <w>mhmh</w>
    <t type="p"></t>

  </u>
  <u who="FAT" uID="u226">
    <w>mis</w>
    <w>häält</w>
    <w>konn</w>
    <w>teeb</w>
    <t type="q"></t>

  </u>
  <u who="CHI" uID="u227">
    <w>hoppa</w>
    <pause symbolic-length="simple"/>
    <w untranscribed="unintelligible">xxx</w>
    <w>juurde</w>
    <t type="p"></t>

  </u>
  <u who="FAT" uID="u228">
    <w>kelle</w>
    <w>juurde</w>
    <w>ta</w>
    <w>läheb</w>
    <t type="q"></t>

  </u>
  <u who="CHI" uID="u229">
    <e><action/></e>
    <t type="p"></t>

  </u>
  <u who="FAT" uID="u230">
    <w>Kevini</w>
    <w>juurde</w>
    <w>või</w>
    <t type="q"></t>

  </u>
  <u who="CHI" uID="u231">
    <w>jah</w>
    <t type="p"></t>

  </u>
  <u who="FAT" uID="u232">
    <w>tohoh</w>
    <t type="e"></t>

  </u>
  <u who="KAJ" uID="u233">
    <w>mis</w>
    <w>ta</w>
    <w>seal</w>
    <w>teeb</w>
    <t type="q"></t>

  </u>
  <u who="CHI" uID="u234">
    <w>näe</w>
    <pause symbolic-length="simple"/>
    <w>tädi</w>
    <t type="p"></t>

    <a type="actions">näitab oma pükse</a>
  </u>
  <u who="KAJ" uID="u235">
    <w>sul</w>
    <w>on</w>
    <w>uued</w>
    <w>püksid</w>
    <pause symbolic-length="simple"/>
    <w>ma</w>
    <w>ei</w>
    <w>olegi</w>
    <w>neid</w>
    <w>näinud</w>
    <t type="p"></t>

  </u>
  <u who="CHI" uID="u236">
    <w>jaa</w>
    <t type="p"></t>

  </u>
  <u who="KAJ" uID="u237">
    <w>mhmh</w>
    <t type="p"></t>

  </u>
  <u who="KAJ" uID="u238">
    <w>soojad</w>
    <w>on</w>
    <w>ka</w>
    <w>või</w>
    <t type="q"></t>

  </u>
  <u who="CHI" uID="u239">
    <w>jaa</w>
    <pause symbolic-length="simple"/>
    <g><w>soojad</w><ga type="comments">imit</ga></g>
    <t type="p"></t>

  </u>
  <u who="KAJ" uID="u240">
    <w>nendega</w>
    <w>on</w>
    <w>hea</w>
    <w>Tallinnasse</w>
    <w>sõita</w>
    <pause symbolic-length="simple"/>
    <w>suurde</w>
    <w>linna</w>
    <w>ja</w>
    <t type="trail off"></t>

  </u>
  <u who="CHI" uID="u241">
    <w>jaa</w>
    <t type="p"></t>

  </u>
  <u who="KAJ" uID="u242">
    <w>siis</w>
    <w>ei</w>
    <w>hakka</w>
    <w>külm</w>
    <t type="p"></t>

  </u>
  <u who="CHI" uID="u243">
    <g><w>ei</w>
    <w>akka<replacement><w>hakka</w></replacement></w><ga type="comments">imit</ga></g>
    <t type="p"></t>

  </u>
  <u who="KAJ" uID="u244">
    <w>mis</w>
    <w>teete</w>
    <w>seal</w>
    <w>Tallinnas</w>
    <w>täna</w>
    <pause symbolic-length="simple"/>
    <w>kus</w>
    <w>te</w>
    <w>lähete</w>
    <w>issiga</w>
    <t type="q"></t>

  </u>
  <u who="CHI" uID="u245">
    <e><action/></e>
    <t type="p"></t>

  </u>
  <u who="FAT" uID="u246">
    <w>lähme</w>
    <w>autot</w>
    <w>vaatama</w>
    <t type="p"></t>

  </u>
  <u who="CHI" uID="u247">
    <e><action/></e>
    <t type="p"></t>

  </u>
  <u who="KAJ" uID="u248">
    <w>lähetegi</w>
    <t type="q"></t>

  </u>
  <u who="CHI" uID="u249">
    <e><action/></e>
    <t type="p"></t>
    <postcode>trn</postcode>

    <a type="actions">noogutab</a>
  </u>
  <u who="KAJ" uID="u250">
    <w>sa</w>
    <w>aitad</w>
    <w>ka</w>
    <w>siis</w>
    <w>vaadata</w>
    <w>ja</w>
    <w>otsida</w>
    <t type="q"></t>

  </u>
  <u who="CHI" uID="u251">
    <w>jaa</w>
    <t type="p"></t>

  </u>
  <u who="KAJ" uID="u252">
    <w>võtad</w>
    <w>selle</w>
    <w>kõige</w>
    <w>ilusama</w>
    <pause symbolic-length="simple"/>
    <w>onju</w>
    <t type="e"></t>

  </u>
  <u who="CHI" uID="u253">
    <e><action/></e>
    <t type="p"></t>

  </u>
  <u who="FAT" uID="u254">
    <w>siis</w>
    <w>lähme</w>
    <w>vaatame</w>
    <w>trolle</w>
    <t type="p"></t>

  </u>
  <u who="FAT" uID="u255">
    <w>see</w>
    <w>on</w>
    <w>sarvedega</w>
    <w>bussid</w>
    <pause symbolic-length="simple"/>
    <w>jah</w>
    <pause symbolic-length="simple"/>
    <w>suured</w>
    <w>bussid</w>
    <w>on</w>
    <w>seal</w>
    <w>Tallinnas</w>
    <pause symbolic-length="simple"/>
    <pause symbolic-length="simple"/>
    <w>ja</w>
    <w>laevad</w>
    <w>on</w>
    <w>ja</w>
    <pause symbolic-length="simple"/>
    <pause symbolic-length="simple"/>
    <w>lennuk</w>
    <w>on</w>
    <w>ka</w>
    <t type="p"></t>

  </u>
  <u who="CHI" uID="u256">
    <w untranscribed="unintelligible">xxx</w>
    <w>ka</w>
    <t type="p"></t>

  </u>
  <u who="CHI" uID="u257">
    <w>näe</w>
    <w>lõvi</w>
    <t type="e"></t>

  </u>
  <u who="KAJ" uID="u258">
    <w>lõvi</w>
    <w>on</w>
    <w>jah</w>
    <t type="p"></t>

  </u>
  <u who="CHI" uID="u259">
    <w>jah</w>
    <t type="p"></t>

  </u>
  <u who="KAJ" uID="u260">
    <w>suur</w>
    <pause symbolic-length="simple"/>
    <pause symbolic-length="simple"/>
    <w>ja</w>
    <w>kuri</w>
    <t type="p"></t>

    <a type="actions">keerab lehte</a>
  </u>
  <u who="KAJ" uID="u261">
    <w>a'</w>
    <w>vaata</w>
    <t type="trail off"></t>

  </u>
  <u who="FAT" uID="u262">
    <w>kes</w>
    <w>seal</w>
    <w>on</w>
    <t type="q"></t>

  </u>
  <u who="CHI" uID="u263">
    <e><action/></e>
    <t type="p"></t>

    <a type="actions">ronib FAT seljas</a>
  </u>
  <u who="FAT" uID="u264">
    <w>ära</w>
    <w>tee</w>
    <t type="e"></t>

  </u>
  <u who="FAT" uID="u265">
    <w>oota</w>
    <pause symbolic-length="simple"/>
    <w>keera</w>
    <w>ise</w>
    <w>lehekülge</w>
    <pause symbolic-length="simple"/>
    <w>vaata</w>
    <w>mis</w>
    <w>siin</w>
    <w>raamatus</w>
    <w>veel</w>
    <w>on</w>
    <t type="e"></t>

  </u>
  <u who="KAJ" uID="u266">
    <w>vaatame</w>
    <pause symbolic-length="simple"/>
    <w>mis</w>
    <w>seal</w>
    <w>tagapool</w>
    <w>veel</w>
    <w>on</w>
    <t type="e"></t>

  </u>
  <u who="KAJ" uID="u267">
    <w>tahad</w>
    <w>keerata</w>
    <w>lehte</w>
    <t type="q"></t>

  </u>
  <u who="CHI" uID="u268">
    <e><action/></e>
    <t type="p"></t>

  </u>
  <u who="FAT" uID="u269">
    <w>see</w>
    <w>on</w>
    <w>huvitav</w>
    <w>raamat</w>
    <pause symbolic-length="simple"/>
    <w>siin</w>
    <w>on</w>
    <w>palju</w>
    <w>loomi</w>
    <t type="p"></t>

  </u>
  <u who="CHI" uID="u270">
    <e><action/></e>
    <t type="p"></t>

  </u>
  <u who="KAJ" uID="u271">
    <w>siin</w>
    <w>on</w>
    <w>kiisu</w>
    <w>kuskil</w>
    <w>taga</w>
    <pause symbolic-length="simple"/>
    <w>ma</w>
    <w>tean</w>
    <t type="p"></t>

    <a type="actions">lehitseb raamatut</a>
  </u>
  <u who="KAJ" uID="u272">
    <w>vaata</w>
    <pause symbolic-length="simple"/>
    <w>kus</w>
    <w>kiisud</w>
    <w>ajavad</w>
    <w>juttu</w>
    <t type="e"></t>

  </u>
  <u who="CHI" uID="u273">
    <e><action/></e>
    <t type="p"></t>

  </u>
  <u who="FAT" uID="u274">
    <w>loeme</w>
    <w>ära</w>
    <pause symbolic-length="simple"/>
    <w>palju</w>
    <w>kiisusi</w>
    <w>on</w>
    <t type="e"></t>

  </u>
  <u who="FAT" uID="u275">
    <w>üks</w>
    <w>kaks</w>
    <w>kolm</w>
    <w>neli</w>
    <pause symbolic-length="simple"/>
    <w>palju</w>
    <w>siin</w>
    <w>on</w>
    <t type="q"></t>

  </u>
  <u who="CHI" uID="u276">
    <e><action/></e>
    <t type="p"></t>

  </u>
  <u who="FAT" uID="u277">
    <w>loeme</w>
    <w>ära</w>
    <t type="e"></t>

  </u>
  <u who="CHI" uID="u278">
    <w>jah</w>
    <t type="p"></t>

  </u>
  <u who="FAT" uID="u279">
    <w>noh</w>
    <w>loe</w>
    <t type="e"></t>

  </u>
  <u who="FAT" uID="u280">
    <w>palju</w>
    <w>on</w>
    <pause symbolic-length="simple"/>
    <w>üks</w>
    <w>kaks</w>
    <w>kolm</w>
    <t type="trail off"></t>

  </u>
  <u who="CHI" uID="u281">
    <e><action/></e>
    <t type="p"></t>

  </u>
  <u who="KAJ" uID="u282">
    <w>a'</w>
    <w>tule</w>
    <w>vaata</w>
    <pause symbolic-length="simple"/>
    <w>väike</w>
    <w>hiirepoiss</w>
    <w>on</w>
    <w>ka</w>
    <pause symbolic-length="simple"/>
    <w>kas</w>
    <w>sa</w>
    <w>leiad</w>
    <pause symbolic-length="simple"/>
    <w>kus</w>
    <w>on</w>
    <w>hiirepoiss</w>
    <t type="q"></t>

  </u>
  <u who="CHI" uID="u283">
    <e><action/></e>
    <t type="p"></t>

  </u>
  <u who="FAT" uID="u284">
    <w>kus</w>
    <w>on</w>
    <w>hiir</w>
    <pause symbolic-length="simple"/>
    <w>otsi</w>
    <w>hiir</w>
    <w>üles</w>
    <pause symbolic-length="simple"/>
    <w>leiad</w>
    <w>hiirt</w>
    <t type="q"></t>

  </u>
  <u who="KAJ" uID="u285">
    <w>näita</w>
    <w>kus</w>
    <w>ta</w>
    <w>on</w>
    <t type="e"></t>

  </u>
  <u who="CHI" uID="u286">
    <e><action/></e>
    <t type="p"></t>
    <postcode>trn</postcode>

    <a type="actions">näitab suvaliselt</a>
  </u>
  <u who="KAJ" uID="u287">
    <w>seal</w>
    <w>või</w>
    <t type="q"></t>

  </u>
  <u who="FAT" uID="u288">
    <w>ei</w>
    <w>ole</w>
    <w>seal</w>
    <pause symbolic-length="simple"/>
    <w>kuskil</w>
    <w>on</w>
    <w>veel</w>
    <t type="p"></t>

  </u>
  <u who="FAT" uID="u289">
    <w>kus</w>
    <w>on</w>
    <w>tillukene</w>
    <w>hiir</w>
    <t type="p"></t>

  </u>
  <u who="CHI" uID="u290">
    <w>ongi</w>
    <g><w>iil<replacement><w>hiir</w></replacement></w><ga type="comments">imit</ga></g>
    <t type="p"></t>

    <a type="actions">näitab</a>
  </u>
  <u who="KAJ" uID="u291">
    <w>jah</w>
    <pause symbolic-length="simple"/>
    <w>on</w>
    <w>jah</w>
    <t type="e"></t>

  </u>
  <u who="KAJ" uID="u292">
    <w>ja</w>
    <w>vaata</w>
    <w>siin</w>
    <w>on</w>
    <w>ka</w>
    <w>veel</w>
    <w>üks</w>
    <t type="e"></t>

  </u>
  <u who="CHI" uID="u293">
    <w>jah</w>
    <t type="p"></t>

  </u>
  <u who="FAT" uID="u294">
    <w>kaks</w>
    <w>hiirt</w>
    <w>on</w>
    <t type="p"></t>

  </u>
  <u who="CHI" uID="u295">
    <w>jah</w>
    <t type="p"></t>

  </u>
  <u who="FAT" uID="u296">
    <w>on</w>
    <w>või</w>
    <t type="q"></t>

  </u>
  <u who="CHI" uID="u297">
    <w>jah</w>
    <t type="p"></t>

  </u>
  <u who="FAT" uID="u298">
    <w>kas</w>
    <w>sa</w>
    <w>Kaja<wk type="cmp"/>tädile</w>
    <w>rääkisid</w>
    <w>et</w>
    <w>sul</w>
    <w>käis</w>
    <w>jõuluvana</w>
    <w>külas</w>
    <t type="q"></t>

  </u>
  <u who="CHI" uID="u299">
    <e><action/></e>
    <t type="p"></t>

  </u>
  <u who="FAT" uID="u300">
    <w>räägi</w>
    <w>mis</w>
    <w>jõuluvana</w>
    <w>tõi</w>
    <t type="e"></t>

  </u>
  <u who="CHI" uID="u301">
    <e><action/></e>
    <t type="p"></t>

  </u>
  <u who="FAT" uID="u302">
    <w>mis</w>
    <w>jõuluvana</w>
    <w>tõi</w>
    <w>pojale</w>
    <t type="q"></t>

  </u>
  <u who="CHI" uID="u303">
    <w>kingi</w>
    <t type="p"></t>

  </u>
  <u who="FAT" uID="u304">
    <w>tõi</w>
    <w>või</w>
    <t type="q"></t>

  </u>
  <u who="CHI" uID="u305">
    <w>jaa</w>
    <t type="p"></t>

  </u>
  <u who="FAT" uID="u306">
    <w>ja</w>
    <w>kes</w>
    <w>veel</w>
    <w>käisid</w>
    <t type="q"></t>

  </u>
  <u who="FAT" uID="u307">
    <w>kes</w>
    <w>külas</w>
    <w>käis</w>
    <t type="q"></t>

  </u>
  <u who="CHI" uID="u308">
    <w>jaa</w>
    <t type="p"></t>

  </u>
  <u who="FAT" uID="u309">
    <w>päkapikk</w>
    <t type="p"></t>

  </u>
  <u who="CHI" uID="u310">
    <w>jah</w>
    <t type="p"></t>

  </u>
  <u who="KAJ" uID="u311">
    <w>mis</w>
    <w>päkapikk</w>
    <w>tõi</w>
    <t type="q"></t>

  </u>
  <u who="CHI" uID="u312">
    <w>kingi</w>
    <t type="p"></t>

  </u>
  <u who="CHI" uID="u313">
    <w>kommi</w>
    <g><w>tõi</w><ga type="comments">imit</ga></g>
    <t type="p"></t>

  </u>
  <u who="CHI" uID="u314">
    <w>kommi</w>
    <g><w>tõi</w><ga type="comments">imit</ga></g>
    <t type="p"></t>

  </u>
  <u who="KAJ" uID="u315">
    <w>ahah</w>
    <t type="p"></t>

  </u>
  <u who="KAJ" uID="u316">
    <w>a'</w>
    <w>kus</w>
    <w>ta</w>
    <w>oskas</w>
    <w>tulla</w>
    <pause symbolic-length="simple"/>
    <w>kus</w>
    <w>ta</w>
    <w>teadis</w>
    <w>et</w>
    <w>sina</w>
    <w>elad</w>
    <w>seal</w>
    <t type="q"></t>

  </u>
  <u who="CHI" uID="u317">
    <w>jaa</w>
    <t type="p"></t>

  </u>
  <u who="KAJ" uID="u318">
    <w>teadis</w>
    <t type="q"></t>

  </u>
  <u who="CHI" uID="u319">
    <w>piilub</w>
    <t type="p"></t>

  </u>
  <u who="KAJ" uID="u320">
    <g><w>piilub</w><ga type="comments">imit</ga></g>
    <t type="q"></t>

  </u>
  <u who="CHI" uID="u321">
    <w>jah</w>
    <t type="p"></t>

  </u>
  <u who="KAJ" uID="u322">
    <w>ta</w>
    <w>piilub</w>
    <w>siis</w>
    <w>igal</w>
    <w>pool</w>
    <pause symbolic-length="simple"/>
    <w>iga</w>
    <w>ukse</w>
    <w>taga</w>
    <w>ja</w>
    <w>vaatab</w>
    <w>akna</w>
    <w>taga</w>
    <t type="q"></t>

  </u>
  <u who="CHI" uID="u323">
    <w>jah</w>
    <t type="p"></t>

  </u>
  <u who="FAT" uID="u324">
    <w>vaata</w>
    <w>kes</w>
    <w>siin</w>
    <w>on</w>
    <t type="e"></t>

    <a type="actions">näitab raamatusse</a>
  </u>
  <u who="CHI" uID="u325">
    <w>vaada<replacement><w>vaata</w></replacement></w>
    <w>lepastiinu<replacement><w>lepatriinu</w></replacement></w>
    <t type="p"></t>

  </u>
  <u who="FAT" uID="u326">
    <w>jah</w>
    <t type="p"></t>

  </u>
  <u who="FAT" uID="u327">
    <w>sipelgas</w>
    <t type="p"></t>

  </u>
  <u who="CHI" uID="u328">
    <w>näe</w>
    <w>uss</w>
    <t type="e"></t>

  </u>
  <u who="KAJ" uID="u329">
    <w>jah</w>
    <t type="p"></t>

  </u>
  <u who="FAT" uID="u330">
    <w>oi</w>
    <t type="e"></t>

  </u>
  <u who="KAJ" uID="u331">
    <w>paks</w>
    <w>uss</w>
    <t type="p"></t>

  </u>
  <u who="CHI" uID="u332">
    <w>näe</w>
    <w>lepatiinu<replacement><w>lepatriinu</w></replacement></w>
    <t type="p"></t>

    <a type="actions">näitab rohutirtsu</a>
  </u>
  <u who="FAT" uID="u333">
    <w>see</w>
    <w>on</w>
    <w>rohutirts</w>
    <t type="p"></t>

  </u>
  <u who="CHI" uID="u334">
    <w>näe</w>
    <t type="e"></t>

  </u>
  <u who="CHI" uID="u335">
    <g><w>näe</w><k type="retracing"/></g>
    <w>näe</w>
    <t type="e"></t>

  </u>
  <u who="FAT" uID="u336">
    <w>see</w>
    <w>on</w>
    <w>mardikas</w>
    <t type="p"></t>

  </u>
  <u who="CHI" uID="u337">
    <w>jah</w>
    <pause symbolic-length="simple"/>
    <g><w>maldikas<replacement><w>mardikas</w></replacement></w><ga type="comments">imit</ga></g>
    <t type="p"></t>

  </u>
  <u who="KAJ" uID="u338">
    <w>a'</w>
    <w>kus</w>
    <w>mesimumm</w>
    <w>on</w>
    <t type="q"></t>

  </u>
  <u who="CHI" uID="u339">
    <w>näe</w>
    <pause symbolic-length="simple"/>
    <w>ongi</w>
    <g><w>mesisumm<replacement><w>mesimumm</w></replacement></w><ga type="comments">imit</ga></g>
    <t type="p"></t>

  </u>
  <u who="FAT" uID="u340">
    <w>mesimumm</w>
    <w>on</w>
    <w>see</w>
    <t type="p"></t>

  </u>
  <u who="CHI" uID="u341">
    <w>ongi</w>
    <w untranscribed="unintelligible">xxx</w>
    <g><w>mesisumm<replacement><w>mesimumm</w></replacement></w><ga type="comments">imit</ga></g>
    <t type="p"></t>

  </u>
  <u who="CHI" uID="u342">
    <w untranscribed="unintelligible">xxx</w>
    <t type="p"></t>

  </u>
  <u who="FAT" uID="u343">
    <w>see</w>
    <w>on</w>
    <w>kiil</w>
    <t type="p"></t>

  </u>
  <u who="CHI" uID="u344">
    <w>näe</w>
    <g><w>kiil</w><ga type="comments">imit</ga></g>
    <t type="e"></t>

  </u>
  <u who="KAJ" uID="u345">
    <w>jah</w>
    <t type="p"></t>

  </u>
  <u who="KAJ" uID="u346">
    <w>ja</w>
    <w>vaata</w>
    <w>ämblik</w>
    <t type="e"></t>

  </u>
  <u who="CHI" uID="u347">
    <w>jah</w>
    <t type="p"></t>

  </u>
  <u who="FAT" uID="u348">
    <w>kus</w>
    <w>liblikas</w>
    <w>on</w>
    <t type="q"></t>

  </u>
  <u who="CHI" uID="u349">
    <g><w>kus</w>
    <w>libikas<replacement><w>liblikas</w></replacement></w>
    <w>on</w><ga type="comments">imit</ga></g>
    <t type="q"></t>

  </u>
  <u who="CHI" uID="u350">
    <w>kus</w>
    <pause symbolic-length="simple"/>
    <w>ongi</w>
    <g><w>libikas<replacement><w>liblikas</w></replacement></w><ga type="comments">imit</ga></g>
    <t type="e"></t>

  </u>
  <u who="FAT" uID="u351">
    <w>ongi</w>
    <t type="e"></t>

  </u>
  <u who="FAT" uID="u352">
    <w>kes</w>
    <w>siin</w>
    <w>veel</w>
    <w>on</w>
    <t type="q"></t>

  </u>
  <u who="CHI" uID="u353">
    <w>näe</w>
    <t type="e"></t>

  </u>
  <u who="FAT" uID="u354">
    <w>ega</w>
    <w>issi</w>
    <w>ka</w>
    <w>ei</w>
    <w>tunne</w>
    <w>kes</w>
    <w>need</w>
    <w>on</w>
    <t type="p"></t>

  </u>
  <u who="CHI" uID="u355">
    <w>jaa</w>
    <t type="p"></t>

  </u>
  <u who="FAT" uID="u356">
    <w>jah</w>
    <t type="p"></t>

  </u>
  <u who="FAT" uID="u357">
    <w>siin</w>
    <w>on</w>
    <w>herilane</w>
    <w>vist</w>
    <t type="p"></t>

  </u>
  <u who="CHI" uID="u358">
    <w>jaa</w>
    <t type="p"></t>

  </u>
  <u who="FAT" uID="u359">
    <w>kes</w>
    <w>see</w>
    <w>on</w>
    <t type="q"></t>

    <a type="actions">näitab kärbest</a>
  </u>
  <u who="CHI" uID="u360">
    <freecode>sosinal</freecode>
    <w>ei</w>
    <w>tea</w>
    <t type="p"></t>

  </u>
  <u who="FAT" uID="u361">
    <w>kärbes</w>
    <t type="p"></t>

  </u>
  <u who="CHI" uID="u362">
    <w>jah</w>
    <pause symbolic-length="simple"/>
    <g><w>käbe<replacement><w>kärbes</w></replacement></w><ga type="comments">imit</ga></g>
    <t type="p"></t>

  </u>
  <u who="FAT" uID="u363">
    <w>mhmh</w>
    <t type="p"></t>

  </u>
  <u who="CHI" uID="u364">
    <w>näe</w>
    <t type="e"></t>

  </u>
  <u who="KAJ" uID="u365">
    <w>sipelgas</w>
    <t type="p"></t>

  </u>
  <u who="CHI" uID="u366">
    <g><w>sipelgas</w><ga type="comments">imit</ga></g>
    <t type="p"></t>

  </u>
  <u who="FAT" uID="u367">
    <w>on</w>
    <w>või</w>
    <t type="q"></t>

  </u>
  <u who="CHI" uID="u368">
    <w>jah</w>
    <t type="p"></t>

  </u>
  <u who="FAT" uID="u369">
    <w>mis</w>
    <w>värvi</w>
    <w>sipelgas</w>
    <w>on</w>
    <t type="q"></t>

  </u>
  <u who="CHI" uID="u370">
    <w>musk<replacement><w>must</w></replacement></w>
    <t type="p"></t>

  </u>
  <u who="FAT" uID="u371">
    <w>täitsa</w>
    <w>must</w>
    <w>on</w>
    <w>jah</w>
    <t type="p"></t>

  </u>
  <u who="FAT" uID="u372">
    <w>aga</w>
    <w>lepatriinu</w>
    <t type="q"></t>

  </u>
  <u who="CHI" uID="u373">
    <w>näe</w>
    <w>ongi</w>
    <w>lepatiinu<replacement><w>lepatriinu</w></replacement></w>
    <t type="p"></t>

  </u>
  <u who="FAT" uID="u374">
    <w>mis</w>
    <w>värvi</w>
    <w>ta</w>
    <w>on</w>
    <t type="q"></t>

  </u>
  <u who="CHI" uID="u375">
    <w>musk<replacement><w>must</w></replacement></w>
    <t type="p"></t>

  </u>
  <u who="FAT" uID="u376">
    <w>mustad</w>
    <w>täpid</w>
    <w>on</w>
    <t type="p"></t>

  </u>
  <u who="CHI" uID="u377">
    <w>jah</w>
    <t type="p"></t>

  </u>
  <u who="FAT" uID="u378">
    <w>aga</w>
    <w>muidu</w>
    <w>on</w>
    <w>ta</w>
    <pause symbolic-length="simple"/>
    <w>punane</w>
    <t type="q"></t>

  </u>
  <u who="CHI" uID="u379">
    <w>jah</w>
    <pause symbolic-length="simple"/>
    <g><w>punane</w><ga type="comments">imit</ga></g>
    <t type="p"></t>

  </u>
  <u who="FAT" uID="u380">
    <w>aga</w>
    <g><w>rohutirts</w><k type="retracing with correction"/></g>
    <w>mis</w>
    <w>värvi</w>
    <w>rohutirts</w>
    <w>on</w>
    <t type="q"></t>

  </u>
  <u who="CHI" uID="u381">
    <w>kollane</w>
    <t type="p"></t>

  </u>
  <u who="FAT" uID="u382">
    <w>ei</w>
    <w>ole</w>
    <w>kollane</w>
    <t type="p"></t>

  </u>
  <u who="CHI" uID="u383">
    <w>see</w>
    <pause symbolic-length="simple"/>
    <w>kollane</w>
    <t type="p"></t>

    <a type="actions">näitab pildile</a>
  </u>
  <u who="FAT" uID="u384">
    <w>see</w>
    <w>on</w>
    <w>kollane</w>
    <w>jah</w>
    <pause symbolic-length="simple"/>
    <w>aga</w>
    <w>see</w>
    <t type="p"></t>

  </u>
  <u who="CHI" uID="u385">
    <w>see</w>
    <g><w>ei</w>
    <w>ole</w><ga type="comments">imit</ga></g>
    <w>kollane</w>
    <t type="p"></t>

  </u>
  <u who="FAT" uID="u386">
    <w>ei</w>
    <w>ole</w>
    <t type="p"></t>

  </u>
  <u who="CHI" uID="u387">
    <w>lohele<replacement><w>roheline</w></replacement></w>
    <t type="p"></t>

  </u>
  <u who="KAJ" uID="u388">
    <w>on</w>
    <w>jaa</w>
    <w>roheline</w>
    <t type="e"></t>

  </u>
  <u who="FAT" uID="u389">
    <w>roheline</w>
    <t type="p"></t>

  </u>
  <u who="KAJ" uID="u390">
    <w>vaata</w>
    <w>see</w>
    <w>auto</w>
    <w>on</w>
    <w>ka</w>
    <w>roheline</w>
    <t type="e"></t>

  </u>
  <u who="CHI" uID="u391">
    <w>jah</w>
    <t type="p"></t>

  </u>
  <u who="FAT" uID="u392">
    <w>kas</w>
    <w>sulle</w>
    <w>meeldivad</w>
    <w>putukad</w>
    <t type="q"></t>

  </u>
  <u who="CHI" uID="u393">
    <w>jah</w>
    <t type="p"></t>

  </u>
  <u who="FAT" uID="u394">
    <w>meeldivad</w>
    <w>või</w>
    <t type="q"></t>

  </u>
  <u who="FAT" uID="u395">
    <w>oi</w>
    <pause symbolic-length="simple"/>
    <pause symbolic-length="simple"/>
    <w>sinust</w>
    <w>tuleb</w>
    <w>bioloog</w>
    <w>siis</w>
    <t type="p"></t>

  </u>
  <u who="CHI" uID="u396">
    <w>jah</w>
    <t type="p"></t>

  </u>
  <u who="FAT" uID="u397">
    <w>no</w>
    <w>vaatame</w>
    <w>edasi</w>
    <t type="e"></t>

  </u>
  <u who="KAJ" uID="u398">
    <w>a'</w>
    <w>mis</w>
    <w>sul</w>
    <w>siin</w>
    <w>soki</w>
    <w>peal</w>
    <w>on</w>
    <pause symbolic-length="simple"/>
    <w>ka</w>
    <w>mõni</w>
    <w>putukas</w>
    <w>või</w>
    <t type="q"></t>

  </u>
  <u who="CHI" uID="u399">
    <w>ei</w>
    <w>ole</w>
    <t type="p"></t>

  </u>
  <u who="KAJ" uID="u400">
    <w>ei</w>
    <w>ole</w>
    <pause symbolic-length="simple"/>
    <w>kes</w>
    <w>see</w>
    <w>on</w>
    <t type="q"></t>

  </u>
  <u who="CHI" uID="u401">
    <w>on</w>
    <pause symbolic-length="simple"/>
    <w>ei</w>
    <w>ole</w>
    <pause symbolic-length="simple"/>
    <w>mesimumm</w>
    <t type="p"></t>

  </u>
  <u who="KAJ" uID="u402">
    <w>mesimumm</w>
    <w>ei</w>
    <w>ole</w>
    <w>jah</w>
    <t type="q"></t>

  </u>
  <u who="CHI" uID="u403">
    <e><action/></e>
    <t type="p"></t>

  </u>
  <u who="FAT" uID="u404">
    <w>keera</w>
    <w>leht</w>
    <w>edasi</w>
    <pause symbolic-length="simple"/>
    <w>vaata</w>
    <w>mis</w>
    <w>sealt</w>
    <w>veel</w>
    <w>tuleb</w>
    <t type="e"></t>

  </u>
  <u who="CHI" uID="u405">
    <e><action/></e>
    <t type="p"></t>
    <postcode>trn</postcode>

    <a type="actions">keerab lehti raamatus</a>
  </u>
  <u who="FAT" uID="u406">
    <w>laul</w>
    <w>on</w>
    <w>siin</w>
    <w>vist</w>
    <t type="p"></t>

  </u>
  <u who="FAT" uID="u407">
    <w>kes</w>
    <w>see</w>
    <w>on</w>
    <t type="q"></t>

  </u>
  <u who="CHI" uID="u408">
    <w untranscribed="unintelligible">xxx</w>
    <t type="p"></t>

  </u>
  <u who="KAJ" uID="u409">
    <w>vaata</w>
    <pause symbolic-length="simple"/>
    <w>mesimummid</w>
    <w>kõik</w>
    <t type="e"></t>

  </u>
  <u who="CHI" uID="u410">
    <w>jah</w>
    <pause symbolic-length="simple"/>
    <g><w>kõik</w><ga type="comments">imit</ga></g>
    <t type="p"></t>

  </u>
  <u who="KAJ" uID="u411">
    <w>hästi</w>
    <w>palju</w>
    <t type="p"></t>

  </u>
  <u who="CHI" uID="u412">
    <w>jah</w>
    <t type="p"></t>

  </u>
  <u who="KAJ" uID="u413">
    <w>mis</w>
    <w>nad</w>
    <w>siin</w>
    <w>teevad</w>
    <t type="q"></t>

  </u>
  <u who="CHI" uID="u414">
    <w>mamm<wk type="cmp"/>mamm<wk type="cmp"/>mamm</w>
    <t type="p"></t>

  </u>
  <u who="KAJ" uID="u415">
    <w>lendlevad</w>
    <w>ringi</w>
    <w>ja</w>
    <w>otsivad</w>
    <w>süüa</w>
    <t type="p"></t>

  </u>
  <u who="CHI" uID="u416">
    <w>jah</w>
    <t type="p"></t>

  </u>
  <u who="FAT" uID="u417">
    <w>kõht</w>
    <w>tühi</w>
    <w>mesilasel</w>
    <t type="p"></t>

  </u>
  <u who="CHI" uID="u418">
    <w>jah</w>
    <t type="p"></t>

  </u>
  <u who="KAJ" uID="u419">
    <w>aga</w>
    <w>need</w>
    <t type="q"></t>

  </u>
  <u who="CHI" uID="u420">
    <w>jah</w>
    <pause symbolic-length="simple"/>
    <w>kutad<replacement><w>kutsad</w></replacement></w>
    <t type="p"></t>

  </u>
  <u who="KAJ" uID="u421">
    <w>kutsad</w>
    <t type="q"></t>

  </u>
  <u who="CHI" uID="u422">
    <w>jah</w>
    <t type="p"></t>

  </u>
  <u who="KAJ" uID="u423">
    <w>ma</w>
    <w>mõtlesin</w>
    <w>et</w>
    <w>lambad</w>
    <t type="e"></t>

  </u>
  <u who="CHI" uID="u424">
    <w>jah</w>
    <g><w>lammad<replacement><w>lambad</w></replacement></w><ga type="comments">imit</ga></g>
    <t type="p"></t>

  </u>
  <u who="KAJ" uID="u425">
    <w>mis</w>
    <w>nemad</w>
    <w>siin</w>
    <w>teevad</w>
    <t type="q"></t>

  </u>
  <u who="CHI" uID="u426">
    <w>muu</w>
    <t type="e"></t>

  </u>
  <u who="KAJ" uID="u427">
    <w>muu</w>
    <t type="p"></t>

  </u>
  <u who="KAJ" uID="u428">
    <w>mää</w>
    <t type="q"></t>

  </u>
  <u who="CHI" uID="u429">
    <g><w>mää</w>
    <w>teevad</w>
    <pause symbolic-length="simple"/>
    <w>mää</w><ga type="comments">imit</ga></g>
    <t type="p"></t>

  </u>
  <u who="KAJ" uID="u430">
    <w>näe</w>
    <w>jooksevad</w>
    <t type="e"></t>

  </u>
  <u who="CHI" uID="u431">
    <w>jah</w>
    <t type="p"></t>

  </u>
  <u who="KAJ" uID="u432">
    <w>ei</w>
    <w>tea</w>
    <w>kus</w>
    <w>nad</w>
    <w>jooksevad</w>
    <pause symbolic-length="simple"/>
    <w>kardavad</w>
    <w>või</w>
    <pause symbolic-length="simple"/>
    <w>mis</w>
    <w>nad</w>
    <w>jooksevad</w>
    <w>siin</w>
    <t type="q"></t>

  </u>
  <u who="CHI" uID="u433">
    <e><action/></e>
    <t type="p"></t>

  </u>
  <u who="FAT" uID="u434">
    <w>hundi</w>
    <w>eest</w>
    <w>jooksevad</w>
    <w>peitu</w>
    <t type="p"></t>

  </u>
  <u who="CHI" uID="u435">
    <w>jah</w>
    <t type="p"></t>

  </u>
  <u who="FAT" uID="u436">
    <w>lähvad</w>
    <w>peitu<wk type="cmp"/>peitu</w>
    <pause symbolic-length="simple"/>
    <pause symbolic-length="simple"/>
    <pause symbolic-length="simple"/>
    <w>ruttu<wk type="cmp"/>ruttu</w>
    <t type="p"></t>

  </u>
  <u who="KAJ" uID="u437">
    <w>aga</w>
    <w>vaata</w>
    <pause symbolic-length="simple"/>
    <w>kes</w>
    <w>siin</w>
    <w>on</w>
    <t type="e"></t>

    <a type="actions">näitab linde</a>
  </u>
  <u who="CHI" uID="u438">
    <w>see</w>
    <g><w>on</w><ga type="comments">imit</ga></g>
    <t type="trail off"></t>

  </u>
  <u who="KAJ" uID="u439">
    <w>ja</w>
    <w>siin</w>
    <pause symbolic-length="simple"/>
    <w>näe</w>
    <pause symbolic-length="simple"/>
    <w>kes</w>
    <w>need</w>
    <w>on</w>
    <t type="q"></t>

  </u>
  <u who="CHI" uID="u440">
    <e><action/></e>
    <t type="p"></t>

  </u>
  <u who="FAT" uID="u441">
    <w>lind</w>
    <w>on</w>
    <t type="p"></t>

  </u>
  <u who="KAJ" uID="u442">
    <w>on</w>
    <w>lind</w>
    <w>või</w>
    <t type="q"></t>

  </u>
  <u who="CHI" uID="u443">
    <e><action/></e>
    <t type="p"></t>

  </u>
  <u who="FAT" uID="u444">
    <w>ei</w>
    <w>ole</w>
    <t type="e"></t>

  </u>
  <u who="CHI" uID="u445">
    <freecode>sosinal</freecode>
    <w>ikka</w>
    <t type="p"></t>

  </u>
  <u who="KAJ" uID="u446">
    <w>ikka</w>
    <w>on</w>
    <t type="q"></t>

  </u>
  <u who="CHI" uID="u447">
    <e><action/></e>
    <t type="p"></t>

  </u>
  <u who="KAJ" uID="u448">
    <w>a'</w>
    <w>räägi</w>
    <w>mis</w>
    <w>sa</w>
    <w>eile</w>
    <w>tegid</w>
    <t type="q"></t>

  </u>
  <u who="CHI" uID="u449">
    <e><action/></e>
    <t type="p"></t>

  </u>
  <u who="KAJ" uID="u450">
    <w>olid</w>
    <w>eile</w>
    <w>kodus</w>
    <w>või</w>
    <t type="q"></t>

  </u>
  <u who="CHI" uID="u451">
    <e><action/></e>
    <t type="p"></t>

  </u>
  <u who="FAT" uID="u452">
    <w>eile</w>
    <w>olid</w>
    <g><w>vanaema</w>
    <w>pool</w><k type="retracing with correction"/></g>
    <g><w>tsilla</w><ga type="explanation">tsintsilla</ga></g>
    <w>vanaema</w>
    <w>pool</w>
    <t type="p"></t>

  </u>
  <u who="CHI" uID="u453">
    <e><action/></e>
    <t type="p"></t>

  </u>
  <u who="FAT" uID="u454">
    <w>jah</w>
    <t type="p"></t>

  </u>
  <u who="KAJ" uID="u455">
    <w>emme</w>
    <w>oli</w>
    <w>ka</w>
    <w>seal</w>
    <w>või</w>
    <t type="q"></t>

  </u>
  <u who="CHI" uID="u456">
    <w>jah</w>
    <t type="p"></t>

  </u>
  <u who="KAJ" uID="u457">
    <w>mis</w>
    <w>te</w>
    <w>tegite</w>
    <w>seal</w>
    <t type="q"></t>

  </u>
  <u who="CHI" uID="u458">
    <e><action/></e>
    <t type="p"></t>

  </u>
  <u who="FAT" uID="u459">
    <w>ütle</w>
    <w>emme</w>
    <w>viis</w>
    <w>kuuse</w>
    <w>välja</w>
    <w>ja</w>
    <t type="p"></t>

  </u>
  <u who="CHI" uID="u460">
    <g><w>emme</w>
    <w>kuuse</w>
    <w>välja</w><ga type="comments">imit</ga></g>
    <t type="p"></t>

  </u>
  <u who="FAT" uID="u461">
    <w>jah</w>
    <pause symbolic-length="simple"/>
    <w>võtsite</w>
    <w>ehted</w>
    <w>küljest</w>
    <w>ära</w>
    <t type="p"></t>

  </u>
  <u who="CHI" uID="u462">
    <w>jaa</w>
    <t type="p"></t>

  </u>
  <u who="FAT" uID="u463">
    <w>kas</w>
    <w>klotsiga</w>
    <w>ka</w>
    <w>mängisid</w>
    <w>või</w>
    <t type="q"></t>

  </u>
  <u who="CHI" uID="u464">
    <e><action/></e>
    <t type="p"></t>

  </u>
  <u who="FAT" uID="u465">
    <w>või</w>
    <w>ei</w>
    <w>mänginud</w>
    <t type="q"></t>

  </u>
  <u who="CHI" uID="u466">
    <e><action/></e>
    <t type="p"></t>

  </u>
  <u who="FAT" uID="u467">
    <w>mis</w>
    <w>sa</w>
    <w>klotsiga</w>
    <w>tegid</w>
    <w>seal</w>
    <pause symbolic-length="simple"/>
    <pause symbolic-length="simple"/>
    <w>kas</w>
    <w>tegid</w>
    <w>looma</w>
    <w>või</w>
    <w>tegid</w>
    <w>maja</w>
    <w>või</w>
    <t type="q"></t>

  </u>
  <u who="CHI" uID="u468">
    <e><action/></e>
    <t type="p"></t>

  </u>
  <u who="FAT" uID="u469">
    <w>mis</w>
    <w>sa</w>
    <w>tegid</w>
    <w>seal</w>
    <t type="q"></t>

  </u>
  <u who="CHI" uID="u470">
    <freecode>sosinal</freecode>
    <g><w>looma</w><ga type="comments">imit</ga></g>
    <t type="p"></t>

  </u>
  <u who="KAJ" uID="u471">
    <w>looma</w>
    <t type="q"></t>

  </u>
  <u who="FAT" uID="u472">
    <w>mhmh</w>
    <t type="p"></t>

  </u>
  <u who="KAJ" uID="u473">
    <w>a'</w>
    <w>mis</w>
    <w>Sanna</w>
    <w>tegi</w>
    <t type="q"></t>

  </u>
  <u who="KAJ" uID="u474">
    <w>Sanna</w>
    <w>oli</w>
    <w>ka</w>
    <w>seal</w>
    <w>eile</w>
    <t type="q"></t>

  </u>
  <u who="CHI" uID="u475">
    <w>jaa</w>
    <t type="p"></t>

  </u>
  <u who="CHI" uID="u476">
    <w>Sanna</w>
    <w>mängis</w>
    <w>küll</w>
    <t type="p"></t>

  </u>
  <u who="KAJ" uID="u477">
    <w>Sanna</w>
    <w>mängis</w>
    <w>jah</w>
    <t type="q"></t>

  </u>
  <u who="CHI" uID="u478">
    <w>jaa</w>
    <t type="p"></t>

  </u>
  <u who="KAJ" uID="u479">
    <w>mis</w>
    <w>ta</w>
    <w>veel</w>
    <w>tegi</w>
    <t type="q"></t>

  </u>
  <u who="CHI" uID="u480">
    <e><action/></e>
    <t type="p"></t>

  </u>
  <u who="FAT" uID="u481">
    <w>kas</w>
    <w>Sanna</w>
    <w>sõi</w>
    <w>ka</w>
    <w>või</w>
    <pause symbolic-length="simple"/>
    <w>oli</w>
    <w>hea</w>
    <w>laps</w>
    <t type="q"></t>

  </u>
  <u who="CHI" uID="u482">
    <g><w>Sanna</w><k type="retracing with correction"/></g>
    <pause symbolic-length="simple"/>
    <w>jõuluvana</w>
    <w>tõi</w>
    <w>kingi</w>
    <w>Sannale</w>
    <t type="p"></t>

  </u>
  <u who="KAJ" uID="u483">
    <w>mida</w>
    <t type="q"></t>

  </u>
  <u who="FAT" uID="u484">
    <w>ahah</w>
    <pause symbolic-length="simple"/>
    <w>jõuluvana</w>
    <w>tõi</w>
    <w>kingi</w>
    <w>Sannale</w>
    <t type="p"></t>

  </u>
  <u who="KAJ" uID="u485">
    <w>aga</w>
    <pause symbolic-length="simple"/>
    <w>kuidas</w>
    <w>sinu</w>
    <w>see</w>
    <w>väike</w>
    <w>tita</w>
    <w>elab</w>
    <pause symbolic-length="simple"/>
    <w>õigemini</w>
    <w>küll</w>
    <w>Sanna</w>
    <w>tita</w>
    <t type="p"></t>

  </u>
  <u who="CHI" uID="u486">
    <w untranscribed="unintelligible">xxx</w>
    <t type="p"></t>

  </u>
  <u who="KAJ" uID="u487">
    <w>see</w>
    <w>kes</w>
    <w>nutab</w>
    <w>ja</w>
    <w>keda</w>
    <w>peab</w>
    <w>kussutama</w>
    <t type="q"></t>

  </u>
  <u who="KAJ" uID="u488">
    <w>saate</w>
    <w>ikka</w>
    <w>hakkama</w>
    <w>ja</w>
    <t type="q"></t>

  </u>
  <u who="CHI" uID="u489">
    <w>jaa</w>
    <t type="p"></t>

  </u>
  <u who="FAT" uID="u490">
    <w>nuku</w>
    <w>on</w>
    <w>seal</w>
    <pause symbolic-length="simple"/>
    <w>Kaja<wk type="cmp"/>tädi</w>
    <w>tõi</w>
    <w>nuku</w>
    <t type="p"></t>

  </u>
  <u who="CHI" uID="u491">
    <w>jah</w>
    <t type="p"></t>

  </u>
  <u who="FAT" uID="u492">
    <w>see</w>
    <w>kes</w>
    <w>nutab</w>
    <w>ää</w>
    <pause symbolic-length="simple"/>
    <w>siis</w>
    <w>sa</w>
    <w>teed</w>
    <w>kaisu<wk type="cmp"/>kaisu</w>
    <pause symbolic-length="simple"/>
    <w>siis</w>
    <w>ta</w>
    <w>hakkab</w>
    <w>naerma</w>
    <t type="p"></t>

  </u>
  <u who="CHI" uID="u493">
    <w>jah</w>
    <t type="p"></t>

  </u>
  <u who="FAT" uID="u494">
    <w>mhmh</w>
    <t type="p"></t>

  </u>
  <u who="KAJ" uID="u495">
    <w>kas</w>
    <w>ta</w>
    <w>on</w>
    <w>hea</w>
    <w>laps</w>
    <pause symbolic-length="simple"/>
    <w>see</w>
    <w>nuku</w>
    <t type="q"></t>

  </u>
  <u who="CHI" uID="u496">
    <w>jah</w>
    <t type="p"></t>

  </u>
  <u who="KAJ" uID="u497">
    <w>probleeme</w>
    <w>ei</w>
    <w>ole</w>
    <t type="q"></t>

  </u>
  <u who="CHI" uID="u498">
    <e><action/></e>
    <t type="p"></t>

    <a type="actions">kisub raamatus lehti</a>
  </u>
  <u who="FAT" uID="u499">
    <w>ära</w>
    <w>seda</w>
    <w>võta</w>
    <pause symbolic-length="simple"/>
    <w>see</w>
    <w>läheb</w>
    <w>katki</w>
    <t type="e"></t>

  </u>
  <u who="KAJ" uID="u500">
    <w>vaata</w>
    <t type="e"></t>

  </u>
  <u who="FAT" uID="u501">
    <w>oo</w>
    <pause symbolic-length="simple"/>
    <w>kes</w>
    <w>siin</w>
    <w>on</w>
    <t type="q"></t>

  </u>
  <u who="FAT" uID="u502">
    <w>kes</w>
    <w>see</w>
    <w>on</w>
    <t type="q"></t>

  </u>
  <u who="CHI" uID="u503">
    <w untranscribed="unintelligible">xxx</w>
    <t type="p"></t>

  </u>
  <u who="FAT" uID="u504">
    <w>hiirepoiss</w>
    <t type="q"></t>

  </u>
  <u who="CHI" uID="u505">
    <w>näe</w>
    <t type="p"></t>

  </u>
  <u who="KAJ" uID="u506">
    <w>jah</w>
    <t type="p"></t>

  </u>
  <u who="CHI" uID="u507">
    <w>onu</w>
    <t type="p"></t>

  </u>
  <u who="FAT" uID="u508">
    <w>kokaonu</w>
    <w>on</w>
    <w>see</w>
    <t type="p"></t>

  </u>
  <u who="CHI" uID="u509">
    <w>jah</w>
    <pause symbolic-length="simple"/>
    <g><w>kokaonu</w><ga type="comments">imit</ga></g>
    <t type="p"></t>

  </u>
  <u who="FAT" uID="u510">
    <w>kokaonu</w>
    <w>teeb</w>
    <w>süüa</w>
    <t type="p"></t>

  </u>
  <u who="CHI" uID="u511">
    <w>jah</w>
    <t type="p"></t>

  </u>
  <u who="KAJ" uID="u512">
    <w>vaata</w>
    <w>siin</w>
    <w>hiirepoiss</w>
    <w>läheb</w>
    <w>vist</w>
    <w>kõigepealt</w>
    <pause symbolic-length="simple"/>
    <pause symbolic-length="simple"/>
    <w>poodi</w>
    <w>või</w>
    <t type="q"></t>

  </u>
  <u who="KAJ" uID="u513">
    <w>näe</w>
    <w>siin</w>
    <w>on</w>
    <w>igatehes</w>
    <w>poes</w>
    <w>ja</w>
    <w>ostab</w>
    <pause symbolic-length="simple"/>
    <pause symbolic-length="simple"/>
    <w>õunu</w>
    <w>ja</w>
    <pause symbolic-length="simple"/>
    <w>apelsine</w>
    <pause symbolic-length="simple"/>
    <w>ja</w>
    <w>siis</w>
    <w>läheb</w>
    <w>koju</w>
    <w>ja</w>
    <w>hakkab</w>
    <w>kokaonuga</w>
    <w>koos</w>
    <w>süüa</w>
    <w>tegema</w>
    <t type="p"></t>

  </u>
  <u who="KAJ" uID="u514">
    <w>vaata</w>
    <pause symbolic-length="simple"/>
    <pause symbolic-length="simple"/>
    <w>saia</w>
    <w>küpsetas</w>
    <t type="p"></t>

  </u>
  <u who="CHI" uID="u515">
    <e><action/></e>
    <t type="p"></t>

  </u>
  <u who="KAJ" uID="u516">
    <w>kas</w>
    <w>sul</w>
    <w>emme</w>
    <w>ka</w>
    <w>vahepeal</w>
    <w>saia</w>
    <w>küpsetab</w>
    <t type="q"></t>

  </u>
  <u who="CHI" uID="u517">
    <w>jaa</w>
    <t type="p"></t>

  </u>
  <u who="KAJ" uID="u518">
    <w>mis</w>
    <w>see</w>
    <w>emme</w>
    <w>veel</w>
    <w>teeb</w>
    <t type="q"></t>

  </u>
  <u who="KAJ" uID="u519">
    <w>õlut</w>
    <w>ka</w>
    <w>teeb</w>
    <w>või</w>
    <t type="q"></t>

  </u>
  <u who="CHI" uID="u520">
    <w>jaa</w>
    <t type="p"></t>

  </u>
  <u who="FAT" uID="u521">
    <w>a'</w>
    <w>kes</w>
    <w>õlut</w>
    <w>joob</w>
    <t type="q"></t>

  </u>
  <u who="CHI" uID="u522">
    <w>emme</w>
    <pause symbolic-length="simple"/>
    <g><w>joob</w>
    <w>õlut</w><ga type="comments">imit</ga></g>
    <t type="p"></t>

  </u>
  <u who="KAJ" uID="u523">
    <w>emme</w>
    <t type="q"></t>

  </u>
  <u who="FAT" uID="u524">
    <w>aga</w>
    <w>issi</w>
    <t type="q"></t>

  </u>
  <u who="CHI" uID="u525">
    <w>jaa</w>
    <t type="p"></t>

  </u>
  <u who="KAJ" uID="u526">
    <w>aga</w>
    <g><w>Santsu</w><ga type="explanation">Sandor</ga></g>
    <t type="q"></t>

  </u>
  <u who="CHI" uID="u527">
    <w>jaa</w>
    <t type="p"></t>

  </u>
  <u who="KAJ" uID="u528">
    <w>Sanna</w>
    <t type="q"></t>

  </u>
  <u who="CHI" uID="u529">
    <w>jaa</w>
    <t type="p"></t>

  </u>
  <u who="KAJ" uID="u530">
    <w>Sanna</w>
    <w>ka</w>
    <w>joob</w>
    <t type="q"></t>

  </u>
  <u who="CHI" uID="u531">
    <w>jah</w>
    <t type="p"></t>

  </u>
  <u who="KAJ" uID="u532">
    <w>ei</w>
    <w>usu</w>
    <t type="p"></t>

  </u>
  <u who="CHI" uID="u533">
    <w>ikka</w>
    <t type="p"></t>

  </u>
  <u who="KAJ" uID="u534">
    <freecode>naerdes</freecode>
    <w>ma</w>
    <w>ei</w>
    <w>usu</w>
    <t type="e"></t>

  </u>
  <u who="CHI" uID="u535">
    <w>ikka</w>
    <t type="p"></t>

  </u>
  <u who="FAT" uID="u536">
    <w>Sanna</w>
    <w>on</w>
    <w>tillukene</w>
    <pause symbolic-length="simple"/>
    <w>Sanna</w>
    <w>ei</w>
    <w>tohi</w>
    <w>juua</w>
    <t type="p"></t>

  </u>
  <u who="CHI" uID="u537">
    <g><w>Sanna</w>
    <w>ei</w>
    <w>tohi</w>
    <w>juua</w><ga type="comments">imit</ga></g>
    <t type="p"></t>

  </u>
  <u who="FAT" uID="u538">
    <w>jah</w>
    <pause symbolic-length="simple"/>
    <w>Sanna</w>
    <w>jääb</w>
    <w>muidu</w>
    <w>purju</w>
    <t type="p"></t>

  </u>
  <u who="CHI" uID="u539">
    <w>jaa</w>
    <t type="p"></t>

  </u>
  <u who="KAJ" uID="u540">
    <w>vaata</w>
    <pause symbolic-length="simple"/>
    <w>ma</w>
    <w>mõtlesin</w>
    <w>et</w>
    <w>äkki</w>
    <w>sa</w>
    <w>tahad</w>
    <w>joonistada</w>
    <t type="q"></t>

    <a type="actions">võtab paberi</a>
  </u>
  <u who="CHI" uID="u541">
    <w>jaa</w>
    <t type="p"></t>

  </u>
  <u who="CHI" uID="u542">
    <w untranscribed="unintelligible">xxx</w>
    <w>issi</w>
    <t type="e"></t>

  </u>
  <u who="FAT" uID="u543">
    <w>mis</w>
    <t type="q"></t>

  </u>
  <u who="KAJ" uID="u544">
    <w>issi</w>
    <w>peab</w>
    <w>joonistama</w>
    <w>või</w>
    <t type="q"></t>

  </u>
  <u who="CHI" uID="u545">
    <w>jaa</w>
    <t type="p"></t>

  </u>
  <u who="FAT" uID="u546">
    <g><w>Santsu</w><ga type="explanation">Sandor</ga></g>
    <w>kõigepealt</w>
    <w>joonistab</w>
    <w>ise</w>
    <t type="p"></t>

  </u>
  <u who="CHI" uID="u547">
    <w>jaa</w>
    <t type="p"></t>

  </u>
  <u who="KAJ" uID="u548">
    <w>mis</w>
    <w>värvi</w>
    <w>sa</w>
    <w>tahad</w>
    <t type="q"></t>

  </u>
  <u who="CHI" uID="u549">
    <w>seda</w>
    <t type="p"></t>

    <a type="actions">võtab musta pliiatsi</a>
  </u>
  <u who="KAJ" uID="u550">
    <w>musta</w>
    <t type="q"></t>

  </u>
  <u who="CHI" uID="u551">
    <w>jah</w>
    <t type="p"></t>

  </u>
  <u who="KAJ" uID="u552">
    <w>noh</w>
    <pause symbolic-length="simple"/>
    <w>mis</w>
    <w>sa</w>
    <w>joonistad</w>
    <t type="q"></t>

  </u>
  <u who="CHI" uID="u553">
    <e><action/></e>
    <t type="p"></t>

    <a type="actions">joonistab</a>
  </u>
  <u who="FAT" uID="u554">
    <w>mis</w>
    <w>see</w>
    <w>on</w>
    <w>nüüd</w>
    <t type="q"></t>

  </u>
  <u who="CHI" uID="u555">
    <w>Sandol<replacement><w>Sandor</w></replacement></w>
    <w>joonitab<replacement><w>joonistab</w></replacement></w>
    <w>päiket<replacement><w>päikest</w></replacement></w>
    <t type="p"></t>

  </u>
  <u who="FAT" uID="u556">
    <w>päikest</w>
    <t type="q"></t>

  </u>
  <u who="FAT" uID="u557">
    <g><w>jaa</w>
    <w>ilus</w>
    <w>päike</w><k type="retracing with correction"/></g>
    <pause symbolic-length="simple"/>
    <w>oi</w>
    <w>kui</w>
    <w>ilus</w>
    <w>päike</w>
    <w>tuli</w>
    <t type="e"></t>

  </u>
  <u who="KAJ" uID="u558">
    <w>mhmh</w>
    <t type="p"></t>

  </u>
  <u who="CHI" uID="u559">
    <w>näe</w>
    <w>tita</w>
    <t type="e"></t>

  </u>
  <u who="FAT" uID="u560">
    <w>tita</w>
    <w>või</w>
    <t type="q"></t>

  </u>
  <u who="CHI" uID="u561">
    <w>jah</w>
    <t type="p"></t>

  </u>
  <u who="FAT" uID="u562">
    <w>kus</w>
    <w>tita</w>
    <w>silm</w>
    <w>on</w>
    <w>siis</w>
    <t type="q"></t>

  </u>
  <u who="CHI" uID="u563">
    <w>näe</w>
    <w>ongi</w>
    <w>tita</w>
    <g><w>silm</w><ga type="comments">imit</ga></g>
    <t type="p"></t>

  </u>
  <u who="KAJ" uID="u564">
    <w>jaa</w>
    <pause symbolic-length="simple"/>
    <w>a'</w>
    <w>kus</w>
    <w>kõrv</w>
    <w>on</w>
    <t type="q"></t>

  </u>
  <u who="CHI" uID="u565">
    <w>siin</w>
    <t type="p"></t>

  </u>
  <u who="FAT" uID="u566">
    <w>joonista</w>
    <w>kõrv</w>
    <w>ka</w>
    <t type="e"></t>

  </u>
  <u who="CHI" uID="u567">
    <e><action/></e>
    <t type="p"></t>
    <postcode>trn</postcode>

    <a type="actions">joonistab</a>
  </u>
  <u who="KAJ" uID="u568">
    <w>niiviisi</w>
    <pause symbolic-length="simple"/>
    <w>mhmh</w>
    <t type="p"></t>

  </u>
  <u who="KAJ" uID="u569">
    <w>tee</w>
    <w>juuksed</w>
    <w>ka</w>
    <w>siis</w>
    <w>kui</w>
    <w>sa</w>
    <w>juba</w>
    <w>teed</w>
    <t type="e"></t>

  </u>
  <u who="CHI" uID="u570">
    <w>jah</w>
    <t type="p"></t>

  </u>
  <u who="KAJ" uID="u571">
    <w>niiviisi</w>
    <w>on</w>
    <w>juuksed</w>
    <pause symbolic-length="simple"/>
    <w>pikad</w>
    <w>juuksed</w>
    <w>on</w>
    <w>või</w>
    <t type="q"></t>

  </u>
  <u who="CHI" uID="u572">
    <w>jah</w>
    <t type="p"></t>

  </u>
  <u who="KAJ" uID="u573">
    <w>kas</w>
    <w>kiisu</w>
    <w>ka</w>
    <w>tuleb</w>
    <w>pildi</w>
    <w>peale</w>
    <t type="q"></t>

  </u>
  <u who="CHI" uID="u574">
    <w>jaa</w>
    <t type="p"></t>

    <a type="actions">joonistab</a>
  </u>
  <u who="KAJ" uID="u575">
    <w>see</w>
    <w>oli</w>
    <w>saba</w>
    <w>või</w>
    <t type="q"></t>

  </u>
  <u who="CHI" uID="u576">
    <w>jah</w>
    <t type="p"></t>

  </u>
  <u who="KAJ" uID="u577">
    <w>muud</w>
    <w>ei</w>
    <w>paista</w>
    <w>pildi</w>
    <w>peale</w>
    <t type="p"></t>

  </u>
  <u who="CHI" uID="u578">
    <w>jah</w>
    <t type="p"></t>

    <a type="actions">joonistab</a>
  </u>
  <u who="CHI" uID="u579">
    <w>näe</w>
    <g><w>kiisu</w><k type="retracing"/></g>
    <w>kiisu</w>
    <t type="e"></t>

  </u>
  <u who="FAT" uID="u580">
    <g><w>kiisu</w><ga type="comments">imit</ga></g>
    <pause symbolic-length="simple"/>
    <w>aga</w>
    <w>joonista</w>
    <w>emme</w>
    <w>ka</w>
    <t type="e"></t>

  </u>
  <u who="CHI" uID="u581">
    <w>jah</w>
    <t type="p"></t>

    <a type="actions">joonistab</a>
  </u>
  <u who="KAJ" uID="u582">
    <w>mhmh</w>
    <t type="p"></t>

  </u>
  <u who="FAT" uID="u583">
    <w>aga</w>
    <w>issi</w>
    <t type="q"></t>

  </u>
  <u who="FAT" uID="u584">
    <w>kas</w>
    <w>issi</w>
    <w>ka</w>
    <w>mahub</w>
    <w>sinna</w>
    <w>peale</w>
    <t type="q"></t>

  </u>
  <u who="CHI" uID="u585">
    <w>jaa</w>
    <t type="p"></t>

  </u>
  <u who="FAT" uID="u586">
    <w>joonista</w>
    <w>issi</w>
    <w>ka</w>
    <w>sinna</w>
    <t type="p"></t>

  </u>
  <u who="KAJ" uID="u587">
    <w>näe</w>
    <pause symbolic-length="simple"/>
    <w>vahepeal</w>
    <w>punast</w>
    <w>kah</w>
    <t type="e"></t>

    <a type="actions">annab punase pliiatsi</a>
  </u>
  <u who="CHI" uID="u588">
    <e><action/></e>
    <t type="p"></t>

    <a type="actions">joonistab</a>
  </u>
  <u who="KAJ" uID="u589">
    <w>mis</w>
    <w>sa</w>
    <w>teed</w>
    <w>nüüd</w>
    <t type="q"></t>

  </u>
  <u who="CHI" uID="u590">
    <e><action/></e>
    <t type="p"></t>

  </u>
  <u who="FAT" uID="u591">
    <w>kes</w>
    <w>see</w>
    <w>sinna</w>
    <w>sai</w>
    <w>nüüd</w>
    <t type="q"></t>

  </u>
  <u who="CHI" uID="u592">
    <e><action/></e>
    <t type="p"></t>

    <a type="actions">otsib uusi pliiatseid</a>
  </u>
  <u who="KAJ" uID="u593">
    <w>mis</w>
    <w>värvi</w>
    <w>see</w>
    <w>on</w>
    <t type="q"></t>

  </u>
  <u who="CHI" uID="u594">
    <w>kolane<replacement><w>kollane</w></replacement></w>
    <t type="p"></t>

  </u>
  <u who="KAJ" uID="u595">
    <w>jaa</w>
    <pause symbolic-length="simple"/>
    <w>kollane</w>
    <t type="p"></t>

  </u>
  <u who="CHI" uID="u596">
    <e><action/></e>
    <t type="p"></t>

    <a type="actions">joonistab</a>
  </u>
  <u who="FAT" uID="u597">
    <w>hele<wk type="cmp"/>hele</w>
    <w>kollane</w>
    <t type="p"></t>

  </u>
  <u who="KAJ" uID="u598">
    <w>oota</w>
    <w>ma</w>
    <w>võtan</w>
    <w>selle</w>
    <w>siit</w>
    <w>alt</w>
    <w>ära</w>
    <t type="p"></t>

    <a type="actions">võtab raamatu alt ära</a>
  </u>
  <u who="KAJ" uID="u599">
    <w>vaata</w>
    <pause symbolic-length="simple"/>
    <w>a'</w>
    <w>punane</w>
    <pause symbolic-length="simple"/>
    <w>ilus</w>
    <w>punane</w>
    <w>on</w>
    <t type="e"></t>

  </u>
  <u who="CHI" uID="u600">
    <w>jah</w>
    <t type="p"></t>

  </u>
  <u who="KAJ" uID="u601">
    <w>mis</w>
    <w>me</w>
    <w>teeme</w>
    <w>punasega</w>
    <t type="q"></t>

  </u>
  <u who="CHI" uID="u602">
    <w>issi</w>
    <t type="p"></t>

  </u>
  <u who="KAJ" uID="u603">
    <w>issi</w>
    <w>või</w>
    <t type="q"></t>

  </u>
  <u who="CHI" uID="u604">
    <w>jah</w>
    <t type="p"></t>

  </u>
  <u who="CHI" uID="u605">
    <g><w>issi</w><k type="retracing"/></g>
    <g><w>teeme</w><ga type="comments">imit</ga></g>
    <w>issi</w>
    <t type="p"></t>

  </u>
  <u who="KAJ" uID="u606">
    <w>a'</w>
    <w>ma</w>
    <w>mõtlesin</w>
    <w>et</w>
    <w>me</w>
    <w>teeme</w>
    <g><w>Santsu</w><ga type="explanation">Sandori</ga></g>
    <w>punasega</w>
    <pause symbolic-length="simple"/>
    <w>kellel</w>
    <w>on</w>
    <w>punased</w>
    <w>püksid</w>
    <w>jalas</w>
    <w>täna</w>
    <t type="q"></t>

  </u>
  <u who="CHI" uID="u607">
    <e><action/></e>
    <t type="p"></t>
    <postcode>trn</postcode>

    <a type="actions">näitab FAT</a>
  </u>
  <u who="KAJ" uID="u608">
    <w>issil</w>
    <w>või</w>
    <t type="q"></t>

  </u>
  <u who="CHI" uID="u609">
    <w>jaa</w>
    <t type="p"></t>

  </u>
  <u who="KAJ" uID="u610">
    <w>issil</w>
    <w>on</w>
    <w>punased</w>
    <w>või</w>
    <t type="q"></t>

  </u>
  <u who="FAT" uID="u611">
    <w>ei</w>
    <w>ole</w>
    <pause symbolic-length="simple"/>
    <w>mis</w>
    <w>värvi</w>
    <w>need</w>
    <w>on</w>
    <pause symbolic-length="simple"/>
    <pause symbolic-length="simple"/>
    <w>sinised</w>
    <t type="q"></t>

  </u>
  <u who="CHI" uID="u612">
    <w>musk<replacement><w>must</w></replacement></w>
    <t type="p"></t>

  </u>
  <u who="FAT" uID="u613">
    <w>must</w>
    <w>peaaegu</w>
    <pause symbolic-length="simple"/>
    <pause symbolic-length="simple"/>
    <w>see</w>
    <w>on</w>
    <w>tumesinine</w>
    <t type="p"></t>

  </u>
  <u who="CHI" uID="u614">
    <w>jah</w>
    <t type="p"></t>

  </u>
  <u who="FAT" uID="u615">
    <g><w>a'</w>
    <w>sinul</w>
    <w>on</w>
    <w>punane</w><k type="retracing with correction"/></g>
    <g><w>Santsul</w><ga type="explanation">Sandoril</ga></g>
    <w>on</w>
    <w>punane</w>
    <t type="p"></t>

  </u>
  <u who="KAJ" uID="u616">
    <e><action/></e>
    <t type="p"></t>

    <a type="actions">joonistab lille</a>
  </u>
  <u who="CHI" uID="u617">
    <w>näe</w>
    <w>lill</w>
    <t type="e"></t>

  </u>
  <u who="KAJ" uID="u618">
    <w>jah</w>
    <t type="p"></t>

  </u>
  <u who="KAJ" uID="u619">
    <w>nüüd</w>
    <w>joonistab</w>
    <g><w>Santsu</w><ga type="explanation">Sandor</ga></g>
    <w>või</w>
    <t type="q"></t>

  </u>
  <u who="CHI" uID="u620">
    <g><w>issi</w><k type="retracing with correction"/></g>
    <w>teeme</w>
    <w>issi</w>
    <t type="p"></t>

  </u>
  <u who="KAJ" uID="u621">
    <w>teeme</w>
    <w>issi</w>
    <w>või</w>
    <t type="q"></t>

  </u>
  <u who="FAT" uID="u622">
    <w>issi</w>
    <w>ei</w>
    <w>oska</w>
    <w>enam</w>
    <t type="p"></t>

  </u>
  <u who="CHI" uID="u623">
    <w>Kaja<wk type="cmp"/>tädi</w>
    <w>oskab</w>
    <t type="p"></t>

  </u>
  <u who="FAT" uID="u624">
    <g><w>Kaja<wk type="cmp"/>tädi</w>
    <w>oskab</w><ga type="comments">imit</ga></g>
    <t type="p"></t>

  </u>
  <u who="CHI" uID="u625">
    <w>jaa</w>
    <t type="p"></t>

  </u>
  <u who="KAJ" uID="u626">
    <w>aga</w>
    <w>mis</w>
    <w>me</w>
    <w>joonistame</w>
    <t type="q"></t>

  </u>
  <u who="CHI" uID="u627">
    <w>siia</w>
    <t type="e"></t>

  </u>
  <u who="KAJ" uID="u628">
    <w>sinna</w>
    <t type="q"></t>

  </u>
  <u who="CHI" uID="u629">
    <w>jah</w>
    <t type="p"></t>

  </u>
  <u who="KAJ" uID="u630">
    <w>aga</w>
    <w>mida</w>
    <w>me</w>
    <w>joonistme</w>
    <w>siia</w>
    <t type="q"></t>

  </u>
  <u who="CHI" uID="u631">
    <w>siia</w>
    <w>levi<replacement><w>lõvi</w></replacement></w>
    <t type="p"></t>

  </u>
  <u who="KAJ" uID="u632">
    <w>lõvi</w>
    <t type="q"></t>

  </u>
  <u who="CHI" uID="u633">
    <w>jah</w>
    <t type="p"></t>

  </u>
  <u who="KAJ" uID="u634">
    <w>aga</w>
    <w>seda</w>
    <w>on</w>
    <w>küll</w>
    <w>väga</w>
    <w>raske</w>
    <w>joonistada</w>
    <t type="p"></t>

  </u>
  <u who="KAJ" uID="u635">
    <w>vaatame</w>
    <w>kas</w>
    <w>kala</w>
    <w>tuleb</w>
    <w>välja</w>
    <w>või</w>
    <t type="q"></t>

    <a type="actions">joonistab</a>
  </u>
  <u who="KAJ" uID="u636">
    <w>on</w>
    <w>see</w>
    <w>kala</w>
    <w>moodi</w>
    <w>või</w>
    <t type="q"></t>

  </u>
  <u who="CHI" uID="u637">
    <w>jah</w>
    <t type="p"></t>

  </u>
  <u who="KAJ" uID="u638">
    <w>silm</w>
    <w>ka</w>
    <w>jah</w>
    <t type="q"></t>

  </u>
  <u who="CHI" uID="u639">
    <w>jah</w>
    <t type="p"></t>

  </u>
  <u who="KAJ" uID="u640">
    <w>mis</w>
    <w>see</w>
    <w>kala</w>
    <w>teeb</w>
    <w>nüüd</w>
    <t type="q"></t>

  </u>
  <u who="CHI" uID="u641">
    <w>sulla<wk type="cmp"/>sulla</w>
    <t type="p"></t>

  </u>
  <u who="KAJ" uID="u642">
    <g><w>sulla<wk type="cmp"/>sulla</w><ga type="comments">imit</ga></g>
    <t type="q"></t>

  </u>
  <u who="CHI" uID="u643">
    <w>näe</w>
    <w>lepatiinu<replacement><w>lepatriinu</w></replacement></w>
    <w>ka</w>
    <t type="e"></t>

  </u>
  <u who="CHI" uID="u644">
    <w>lepatiinu<replacement><w>lepatriinu</w></replacement></w>
    <w>ka</w>
    <t type="e"></t>

  </u>
  <u who="KAJ" uID="u645">
    <w>lepatriinu</w>
    <t type="q"></t>

  </u>
  <u who="CHI" uID="u646">
    <w>jah</w>
    <t type="p"></t>

  </u>
  <u who="KAJ" uID="u647">
    <e><action/></e>
    <t type="p"></t>

    <a type="actions">joonistab</a>
  </u>
  <u who="CHI" uID="u648">
    <w untranscribed="unintelligible">xxx</w>
    <t type="p"></t>

  </u>
  <u who="CHI" uID="u649">
    <w untranscribed="unintelligible">xxx</w>
    <w>ka</w>
    <t type="p"></t>

  </u>
  <u who="KAJ" uID="u650">
    <w>näe</w>
    <w>täpid</w>
    <w>ka</w>
    <w>tulevad</w>
    <t type="p"></t>

  </u>
  <u who="KAJ" uID="u651">
    <w>jalad</w>
    <w>ka</w>
    <w>teeme</w>
    <w>või</w>
    <t type="q"></t>

  </u>
  <u who="CHI" uID="u652">
    <w>jaa</w>
    <pause symbolic-length="simple"/>
    <g><w>teeme</w>
    <pause symbolic-length="simple"/>
    <w>jalad</w><ga type="comments">imit</ga></g>
    <t type="p"></t>

  </u>
  <u who="KAJ" uID="u653">
    <w>a'</w>
    <w>nüüd</w>
    <w>joonistab</w>
    <g><w>Santsu</w><ga type="explanation">Sandor</ga></g>
    <w>või</w>
    <t type="q"></t>

  </u>
  <u who="CHI" uID="u654">
    <e><action/></e>
    <t type="p"></t>

    <a type="actions">joonistab</a>
  </u>
  <u who="KAJ" uID="u655">
    <w>joonista</w>
    <w>üks</w>
    <w>päkapikk</w>
    <pause symbolic-length="simple"/>
    <w>kuidas</w>
    <w>päkapikk</w>
    <w>piilub</w>
    <t type="e"></t>

  </u>
  <u who="CHI" uID="u656">
    <w>jah</w>
    <t type="p"></t>

  </u>
  <u who="KAJ" uID="u657">
    <w>niiviisi</w>
    <t type="q"></t>

  </u>
  <u who="CHI" uID="u658">
    <w>jaa</w>
    <t type="p"></t>

    <a type="actions">võtab uue pliiatsi paki seest</a>
  </u>
  <u who="KAJ" uID="u659">
    <w>mhmh</w>
    <t type="p"></t>

  </u>
  <u who="KAJ" uID="u660">
    <w>mis</w>
    <w>värvi</w>
    <w>sa</w>
    <w>nüüd</w>
    <w>võtad</w>
    <t type="q"></t>

  </u>
  <u who="CHI" uID="u661">
    <w untranscribed="unintelligible">xxx</w>
    <w>tuleb</w>
    <w>välja</w>
    <t type="p"></t>

  </u>
  <u who="KAJ" uID="u662">
    <w>selle</w>
    <w>võtad</w>
    <w>mis</w>
    <w>välja</w>
    <w>tuleb</w>
    <t type="q"></t>

  </u>
  <u who="CHI" uID="u663">
    <w>tule</w>
    <w>välja</w>
    <t type="e"></t>

  </u>
  <u who="CHI" uID="u664">
    <w>tule</w>
    <w>välja</w>
    <w>peidust</w>
    <w>välja</w>
    <t type="e"></t>

  </u>
  <u who="CHI" uID="u665">
    <w>tule</w>
    <t type="e"></t>

    <a type="comments">ei litereeri</a>
  </u>
  <u who="CHI" uID="u666">
    <w untranscribed="unintelligible">xxx</w>
    <t type="p"></t>

  </u>
  <u who="KAJ" uID="u667">
    <w>ah</w>
    <w>seda</w>
    <w>sa</w>
    <w>tahadki</w>
    <w>kes</w>
    <w>seal</w>
    <w>peidus</w>
    <w>on</w>
    <w>just</w>
    <t type="e"></t>

  </u>
  <u who="CHI" uID="u668">
    <w>jah</w>
    <t type="p"></t>

  </u>
  <u who="CHI" uID="u669">
    <w>ongi</w>
    <t type="p"></t>

  </u>
  <u who="KAJ" uID="u670">
    <w>noh</w>
    <t type="q"></t>

  </u>
  <u who="CHI" uID="u671">
    <w>noh</w>
    <w>tule</w>
    <pause symbolic-length="simple"/>
    <w>välja</w>
    <t type="e"></t>

  </u>
  <u who="KAJ" uID="u672">
    <w>näed</w>
    <pause symbolic-length="simple"/>
    <w>tuligi</w>
    <w>välja</w>
    <t type="e"></t>

  </u>
  <u who="FAT" uID="u673">
    <w>oh</w>
    <w>sa</w>
    <w>poiss</w>
    <t type="e"></t>

  </u>
  <u who="CHI" uID="u674">
    <w>näe</w>
    <t type="e"></t>

  </u>
  <u who="KAJ" uID="u675">
    <w>kuulas</w>
    <w>sul</w>
    <w>sõna</w>
    <w>ikka</w>
    <t type="q"></t>

  </u>
  <u who="CHI" uID="u676">
    <w>jaa</w>
    <t type="p"></t>

  </u>
  <u who="CHI" uID="u677">
    <w untranscribed="unintelligible">xxx</w>
    <t type="p"></t>

  </u>
  <u who="FAT" uID="u678">
    <w>kes</w>
    <w>see</w>
    <w>on</w>
    <pause symbolic-length="simple"/>
    <w>lilla</w>
    <t type="e"></t>

  </u>
  <u who="FAT" uID="u679">
    <w>eile</w>
    <w>sa</w>
    <w>õppisid</w>
    <w>et</w>
    <w>on</w>
    <w>lilla</w>
    <w>üks</w>
    <w>värv</w>
    <t type="p"></t>

  </u>
  <u who="CHI" uID="u680">
    <e><action/></e>
    <t type="p"></t>

    <a type="actions">joonistab</a>
  </u>
  <u who="KAJ" uID="u681">
    <w>värvid</w>
    <w>lepatriinu</w>
    <w>seest</w>
    <w>ära</w>
    <w>jah</w>
    <t type="q"></t>

  </u>
  <u who="CHI" uID="u682">
    <w>jaa</w>
    <t type="p"></t>

  </u>
  <u who="KAJ" uID="u683">
    <w>vaata</w>
    <pause symbolic-length="simple"/>
    <w>teeme</w>
    <w>siia</w>
    <w>kalale</w>
    <w>vett</w>
    <w>ka</w>
    <w>sinisega</w>
    <pause symbolic-length="simple"/>
    <w>sinine</w>
    <w>vesi</w>
    <t type="p"></t>

    <a type="actions">joonistab</a>
  </u>
  <u who="CHI" uID="u684">
    <w>jaa</w>
    <t type="p"></t>

  </u>
  <u who="KAJ" uID="u685">
    <w>kala</w>
    <w>muidu</w>
    <w>ei</w>
    <w>saa</w>
    <w>ujuda</w>
    <pause symbolic-length="simple"/>
    <pause symbolic-length="simple"/>
    <w>kui</w>
    <w>vett</w>
    <w>ei</w>
    <w>ole</w>
    <t type="p"></t>

  </u>
  <u who="CHI" uID="u686">
    <w>jah</w>
    <t type="p"></t>

  </u>
  <u who="KAJ" uID="u687">
    <w>nüüd</w>
    <w>saab</w>
    <w>ujuda</w>
    <t type="q"></t>

  </u>
  <u who="CHI" uID="u688">
    <w>jaa</w>
    <t type="p"></t>

  </u>
  <u who="KAJ" uID="u689">
    <w>kas</w>
    <w>sa</w>
    <w>ka</w>
    <w>ujuda</w>
    <w>oskad</w>
    <t type="q"></t>

  </u>
  <u who="CHI" uID="u690">
    <w>jaa</w>
    <t type="p"></t>

  </u>
  <u who="KAJ" uID="u691">
    <w>käid</w>
    <w>ujumas</w>
    <t type="q"></t>

  </u>
  <u who="CHI" uID="u692">
    <w>jaa</w>
    <t type="p"></t>

  </u>
  <u who="FAT" uID="u693">
    <w>sa</w>
    <w>käid</w>
    <w>saunas</w>
    <w>ka</w>
    <t type="e"></t>

  </u>
  <u who="CHI" uID="u694">
    <g><w>saunas</w>
    <w>ka</w><ga type="comments">imit</ga></g>
    <t type="p"></t>

  </u>
  <u who="FAT" uID="u695">
    <g><w>a'</w>
    <w>kes</w>
    <w>sul</w>
    <w>saunas</w>
    <w>on</w><k type="retracing with correction"/></g>
    <pause symbolic-length="simple"/>
    <w>mis</w>
    <w>loomad</w>
    <w>sul</w>
    <w>seal</w>
    <w>on</w>
    <t type="q"></t>

  </u>
  <u who="CHI" uID="u696">
    <w>palt<replacement><w>part</w></replacement></w>
    <w>sulla<wk type="cmp"/>sulla</w>
    <t type="p"></t>

  </u>
  <u who="FAT" uID="u697">
    <w>ja</w>
    <w>see</w>
    <w>kilpkonn</w>
    <w>on</w>
    <w>ka</w>
    <t type="p"></t>

  </u>
  <u who="CHI" uID="u698">
    <g><w>kilpkonn</w>
    <w>ka</w><ga type="comments">imit</ga></g>
    <t type="p"></t>

  </u>
</CHAT>